{"users":[{"id":158128894,"id_str":"158128894","name":"Nina Garcia","screen_name":"ninagarcia","location":"NYC","profile_location":null,"description":"Official Account - Nina Garcia, Marie Claire Creative Director & Project Runway Judge - Twitter Oficial de Nina Garcia","url":"http://t.co/aZDEjRCc2l","entities":{"url":{"urls":[{"url":"http://t.co/aZDEjRCc2l","expanded_url":"http://www.ninagarcia.com","display_url":"ninagarcia.com","indices":[0,22]}]},"description":{"urls":[]}},"protected":false,"followers_count":1709821,"friends_count":1018,"listed_count":6028,"created_at":"Mon Jun 21 21:32:40 +0000 2010","favourites_count":317,"utc_offset":-18000,"time_zone":"Eastern Time (US & Canada)","geo_enabled":true,"verified":true,"statuses_count":17649,"lang":"en","contributors_enabled":false,"is_translator":false,"is_translation_enabled":false,"profile_background_color":"131516","profile_background_image_url":"http://pbs.twimg.com/profile_background_images/378800000097353573/677ac475f6e499041407c32b03df31e7.jpeg","profile_background_image_url_https":"https://pbs.twimg.com/profile_background_images/378800000097353573/677ac475f6e499041407c32b03df31e7.jpeg","profile_background_tile":true,"profile_image_url":"http://pbs.twimg.com/profile_images/1551145366/ng_normal.jpg","profile_image_url_https":"https://pbs.twimg.com/profile_images/1551145366/ng_normal.jpg","profile_banner_url":"https://pbs.twimg.com/profile_banners/158128894/1398609020","profile_link_color":"000000","profile_sidebar_border_color":"000000","profile_sidebar_fill_color":"DBD7D0","profile_text_color":"333333","profile_use_background_image":true,"default_profile":false,"default_profile_image":false,"following":false,"follow_request_sent":false,"notifications":false},{"id":24407244,"id_str":"24407244","name":"Dita Von Teese","screen_name":"DitaVonTeese","location":"Hollywood ","profile_location":null,"description":"For bookings, email management@dita.net \nhttp://t.co/LyZQmnCJP5 http://t.co/ijtcC1jJuC","url":"http://t.co/Oskmcu1c33","entities":{"url":{"urls":[{"url":"http://t.co/Oskmcu1c33","expanded_url":"http://www.dita.net","display_url":"dita.net","indices":[0,22]}]},"description":{"urls":[{"url":"http://t.co/LyZQmnCJP5","expanded_url":"http://www.whosay.com/ditavonteese","display_url":"whosay.com/ditavonteese","indices":[41,63]},{"url":"http://t.co/ijtcC1jJuC","expanded_url":"http://www.facebook.com/ditavonteese","display_url":"facebook.com/ditavonteese","indices":[64,86]}]}},"protected":false,"followers_count":1737830,"friends_count":761,"listed_count":14260,"created_at":"Sat Mar 14 18:24:31 +0000 2009","favourites_count":2830,"utc_offset":-28800,"time_zone":"Pacific Time (US & Canada)","geo_enabled":false,"verified":true,"statuses_count":6994,"lang":"en","contributors_enabled":false,"is_translator":false,"is_translation_enabled":false,"profile_background_color":"57212A","profile_background_image_url":"http://pbs.twimg.com/profile_background_images/378800000100486298/61ee86214d79b7ab61290d6c3901a4ab.jpeg","profile_background_image_url_https":"https://pbs.twimg.com/profile_background_images/378800000100486298/61ee86214d79b7ab61290d6c3901a4ab.jpeg","profile_background_tile":false,"profile_image_url":"http://pbs.twimg.com/profile_images/378800000638352613/e47a12565f24ccaca10f1a9ca3743cd1_normal.jpeg","profile_image_url_https":"https://pbs.twimg.com/profile_images/378800000638352613/e47a12565f24ccaca10f1a9ca3743cd1_normal.jpeg","profile_banner_url":"https://pbs.twimg.com/profile_banners/24407244/1382558869","profile_link_color":"141313","profile_sidebar_border_color":"000000","profile_sidebar_fill_color":"CC1250","profile_text_color":"1F190C","profile_use_background_image":true,"default_profile":false,"default_profile_image":false,"following":false,"follow_request_sent":false,"notifications":false},{"id":28061932,"id_str":"28061932","name":"Whitney Cummings","screen_name":"WhitneyCummings","location":"Twitter","profile_location":null,"description":"don't fall in love with me","url":"http://t.co/xCGqoMUkN3","entities":{"url":{"urls":[{"url":"http://t.co/xCGqoMUkN3","expanded_url":"http://www.nbc.com/whitney/","display_url":"nbc.com/whitney/","indices":[0,22]}]},"description":{"urls":[]}},"protected":false,"followers_count":1120655,"friends_count":351,"listed_count":10308,"created_at":"Wed Apr 01 06:11:05 +0000 2009","favourites_count":1730,"utc_offset":-28800,"time_zone":"Pacific Time (US & Canada)","geo_enabled":false,"verified":true,"statuses_count":6815,"lang":"en","contributors_enabled":false,"is_translator":false,"is_translation_enabled":false,"profile_background_color":"DBE9ED","profile_background_image_url":"http://abs.twimg.com/images/themes/theme17/bg.gif","profile_background_image_url_https":"https://abs.twimg.com/images/themes/theme17/bg.gif","profile_background_tile":false,"profile_image_url":"http://pbs.twimg.com/profile_images/481601706955124736/ftMmSNwT_normal.jpeg","profile_image_url_https":"https://pbs.twimg.com/profile_images/481601706955124736/ftMmSNwT_normal.jpeg","profile_banner_url":"https://pbs.twimg.com/profile_banners/28061932/1411506292","profile_link_color":"CC3366","profile_sidebar_border_color":"DBE9ED","profile_sidebar_fill_color":"E6F6F9","profile_text_color":"333333","profile_use_background_image":true,"default_profile":false,"default_profile_image":false,"following":false,"follow_request_sent":false,"notifications":false},{"id":571202103,"id_str":"571202103","name":"Medium","screen_name":"Medium","location":"San Francisco, CA, US","profile_location":null,"description":"Everyone’s stories and ideas","url":"http://t.co/39nrCKtdRI","entities":{"url":{"urls":[{"url":"http://t.co/39nrCKtdRI","expanded_url":"http://medium.com","display_url":"medium.com","indices":[0,22]}]},"description":{"urls":[]}},"protected":false,"followers_count":985101,"friends_count":116,"listed_count":6753,"created_at":"Fri May 04 20:16:39 +0000 2012","favourites_count":1869,"utc_offset":-28800,"time_zone":"Pacific Time (US & Canada)","geo_enabled":false,"verified":true,"statuses_count":8710,"lang":"en","contributors_enabled":false,"is_translator":false,"is_translation_enabled":false,"profile_background_color":"FFFFFF","profile_background_image_url":"http://abs.twimg.com/images/themes/theme14/bg.gif","profile_background_image_url_https":"https://abs.twimg.com/images/themes/theme14/bg.gif","profile_background_tile":true,"profile_image_url":"http://pbs.twimg.com/profile_images/498896933360898049/Io6eZONw_normal.jpeg","profile_image_url_https":"https://pbs.twimg.com/profile_images/498896933360898049/Io6eZONw_normal.jpeg","profile_banner_url":"https://pbs.twimg.com/profile_banners/571202103/1400194510","profile_link_color":"53A663","profile_sidebar_border_color":"FFFFFF","profile_sidebar_fill_color":"EFEFEF","profile_text_color":"333333","profile_use_background_image":false,"default_profile":false,"default_profile_image":false,"following":false,"follow_request_sent":false,"notifications":false},{"id":12611642,"id_str":"12611642","name":"thinkgeek","screen_name":"thinkgeek","location":"Fairfax, VA","profile_location":null,"description":"Cool products for technophiles, geeks, and the occasional monkey. Follow @thinkgeekspam for our new product feed.","url":"http://t.co/gXEYqYTjhg","entities":{"url":{"urls":[{"url":"http://t.co/gXEYqYTjhg","expanded_url":"http://www.thinkgeek.com","display_url":"thinkgeek.com","indices":[0,22]}]},"description":{"urls":[]}},"protected":false,"followers_count":870150,"friends_count":240256,"listed_count":18191,"created_at":"Wed Jan 23 20:36:46 +0000 2008","favourites_count":110,"utc_offset":-18000,"time_zone":"Eastern Time (US & Canada)","geo_enabled":false,"verified":true,"statuses_count":82529,"lang":"en","contributors_enabled":false,"is_translator":false,"is_translation_enabled":false,"profile_background_color":"2E3B41","profile_background_image_url":"http://pbs.twimg.com/profile_background_images/495275287689437184/_RumRcBG.jpeg","profile_background_image_url_https":"https://pbs.twimg.com/profile_background_images/495275287689437184/_RumRcBG.jpeg","profile_background_tile":false,"profile_image_url":"http://pbs.twimg.com/profile_images/3522713236/268f433597dc1e82d2eafcfb9c5c5b20_normal.png","profile_image_url_https":"https://pbs.twimg.com/profile_images/3522713236/268f433597dc1e82d2eafcfb9c5c5b20_normal.png","profile_banner_url":"https://pbs.twimg.com/profile_banners/12611642/1406634290","profile_link_color":"3CBBFB","profile_sidebar_border_color":"FFFFFF","profile_sidebar_fill_color":"1A1A1A","profile_text_color":"9E730B","profile_use_background_image":true,"default_profile":false,"default_profile_image":false,"following":false,"follow_request_sent":false,"notifications":false},{"id":15112070,"id_str":"15112070","name":"Cirque du Soleil ","screen_name":"Cirque","location":"Montreal // Las Vegas","profile_location":null,"description":"We are Cirque du Soleil - we currently have 18 productions worldwide. Follow us for insider info & promotions!","url":"http://t.co/qxfoSlIFbM","entities":{"url":{"urls":[{"url":"http://t.co/qxfoSlIFbM","expanded_url":"http://cirk.me/tweetcds","display_url":"cirk.me/tweetcds","indices":[0,22]}]},"description":{"urls":[]}},"protected":false,"followers_count":651448,"friends_count":36057,"listed_count":5152,"created_at":"Fri Jun 13 22:20:35 +0000 2008","favourites_count":9586,"utc_offset":-28800,"time_zone":"Pacific Time (US & Canada)","geo_enabled":false,"verified":true,"statuses_count":17921,"lang":"en","contributors_enabled":false,"is_translator":false,"is_translation_enabled":false,"profile_background_color":"000000","profile_background_image_url":"http://pbs.twimg.com/profile_background_images/435774308191719425/sQcl1TXE.jpeg","profile_background_image_url_https":"https://pbs.twimg.com/profile_background_images/435774308191719425/sQcl1TXE.jpeg","profile_background_tile":false,"profile_image_url":"http://pbs.twimg.com/profile_images/466211065760468992/Ls51BpB4_normal.jpeg","profile_image_url_https":"https://pbs.twimg.com/profile_images/466211065760468992/Ls51BpB4_normal.jpeg","profile_banner_url":"https://pbs.twimg.com/profile_banners/15112070/1399988375","profile_link_color":"6F15AB","profile_sidebar_border_color":"FFFFFF","profile_sidebar_fill_color":"95E8EC","profile_text_color":"3C3940","profile_use_background_image":true,"default_profile":false,"default_profile_image":false,"following":false,"follow_request_sent":false,"notifications":false},{"id":1183041,"id_str":"1183041","name":"Wil Wheaton","screen_name":"wilw","location":"Los Angeles","profile_location":null,"description":"I'm just this guy, you know?","url":"http://t.co/UAYYOhbijM","entities":{"url":{"urls":[{"url":"http://t.co/UAYYOhbijM","expanded_url":"http://wilwheaton.net/2009/02/what-to-expect-if-you-follow-me-on-twitter-or-how-im-going-to-disappoint-you-in-6-quick-steps/","display_url":"wilwheaton.net/2009/02/what-t…","indices":[0,22]}]},"description":{"urls":[]}},"protected":false,"followers_count":2722957,"friends_count":345,"listed_count":37967,"created_at":"Wed Mar 14 21:25:33 +0000 2007","favourites_count":358,"utc_offset":-28800,"time_zone":"Pacific Time (US & Canada)","geo_enabled":false,"verified":true,"statuses_count":51680,"lang":"en","contributors_enabled":false,"is_translator":false,"is_translation_enabled":true,"profile_background_color":"022330","profile_background_image_url":"http://pbs.twimg.com/profile_background_images/871683408/62c85b46792dfe6bfd16420b71646cdb.png","profile_background_image_url_https":"https://pbs.twimg.com/profile_background_images/871683408/62c85b46792dfe6bfd16420b71646cdb.png","profile_background_tile":true,"profile_image_url":"http://pbs.twimg.com/profile_images/528600852756303872/tRlEoF3B_normal.png","profile_image_url_https":"https://pbs.twimg.com/profile_images/528600852756303872/tRlEoF3B_normal.png","profile_banner_url":"https://pbs.twimg.com/profile_banners/1183041/1368668860","profile_link_color":"0084B4","profile_sidebar_border_color":"000000","profile_sidebar_fill_color":"C0DFEC","profile_text_color":"333333","profile_use_background_image":true,"default_profile":false,"default_profile_image":false,"following":false,"follow_request_sent":false,"notifications":false},{"id":524396430,"id_str":"524396430","name":"Upworthy","screen_name":"Upworthy","location":"The Internet","profile_location":null,"description":"Things that matter. Pass 'em on.","url":"http://t.co/V4EWQCnc56","entities":{"url":{"urls":[{"url":"http://t.co/V4EWQCnc56","expanded_url":"http://www.upworthy.com","display_url":"upworthy.com","indices":[0,22]}]},"description":{"urls":[]}},"protected":false,"followers_count":440632,"friends_count":1442,"listed_count":4571,"created_at":"Wed Mar 14 14:20:33 +0000 2012","favourites_count":1139,"utc_offset":-18000,"time_zone":"Eastern Time (US & Canada)","geo_enabled":false,"verified":true,"statuses_count":12808,"lang":"en","contributors_enabled":false,"is_translator":false,"is_translation_enabled":false,"profile_background_color":"EB7010","profile_background_image_url":"http://pbs.twimg.com/profile_background_images/378800000096112740/8fb3d3a69cc57a3b6788e30f4a05f3f1.jpeg","profile_background_image_url_https":"https://pbs.twimg.com/profile_background_images/378800000096112740/8fb3d3a69cc57a3b6788e30f4a05f3f1.jpeg","profile_background_tile":false,"profile_image_url":"http://pbs.twimg.com/profile_images/378800000615185360/1994e844c23204e40701a4daf07c4aef_normal.png","profile_image_url_https":"https://pbs.twimg.com/profile_images/378800000615185360/1994e844c23204e40701a4daf07c4aef_normal.png","profile_banner_url":"https://pbs.twimg.com/profile_banners/524396430/1378234436","profile_link_color":"225A7A","profile_sidebar_border_color":"FFFFFF","profile_sidebar_fill_color":"DDEEF6","profile_text_color":"333333","profile_use_background_image":false,"default_profile":false,"default_profile_image":false,"following":false,"follow_request_sent":false,"notifications":false},{"id":16267101,"id_str":"16267101","name":"Museum Nerd","screen_name":"museumnerd","location":"Brooklyn, New York","profile_location":null,"description":"Museums. Art. History. Art History. Education. Museology. Historiography. Logophilia. Punnery. I often post as I explore museum exhibits. I am a museum nerd.","url":"http://t.co/rxI2EDLaq0","entities":{"url":{"urls":[{"url":"http://t.co/rxI2EDLaq0","expanded_url":"http://museumnerd.org","display_url":"museumnerd.org","indices":[0,22]}]},"description":{"urls":[]}},"protected":false,"followers_count":198861,"friends_count":3110,"listed_count":3623,"created_at":"Sat Sep 13 01:54:23 +0000 2008","favourites_count":1330,"utc_offset":-18000,"time_zone":"Eastern Time (US & Canada)","geo_enabled":true,"verified":false,"statuses_count":23437,"lang":"en","contributors_enabled":false,"is_translator":false,"is_translation_enabled":false,"profile_background_color":"6F947E","profile_background_image_url":"http://pbs.twimg.com/profile_background_images/90676053/InformationPlusBackground.jpg","profile_background_image_url_https":"https://pbs.twimg.com/profile_background_images/90676053/InformationPlusBackground.jpg","profile_background_tile":false,"profile_image_url":"http://pbs.twimg.com/profile_images/802065582/twitter-museumnerd_normal.jpg","profile_image_url_https":"https://pbs.twimg.com/profile_images/802065582/twitter-museumnerd_normal.jpg","profile_banner_url":"https://pbs.twimg.com/profile_banners/16267101/1356981581","profile_link_color":"005273","profile_sidebar_border_color":"322DB5","profile_sidebar_fill_color":"56944E","profile_text_color":"124712","profile_use_background_image":true,"default_profile":false,"default_profile_image":false,"following":false,"follow_request_sent":false,"notifications":false},{"id":16825289,"id_str":"16825289","name":"CollegeHumor","screen_name":"CollegeHumor","location":"NYC","profile_location":null,"description":"The Official Twitter of CollegeHumor.\n\nhttp://t.co/kdpgCW7PPH http://t.co/4zNF3q3kep","url":"http://t.co/tnp1u2kHNC","entities":{"url":{"urls":[{"url":"http://t.co/tnp1u2kHNC","expanded_url":"http://www.collegehumor.com","display_url":"collegehumor.com","indices":[0,22]}]},"description":{"urls":[{"url":"http://t.co/kdpgCW7PPH","expanded_url":"http://www.facebook.com/collegehumor","display_url":"facebook.com/collegehumor","indices":[39,61]},{"url":"http://t.co/4zNF3q3kep","expanded_url":"http://instagram.com/collegehumor","display_url":"instagram.com/collegehumor","indices":[62,84]}]}},"protected":false,"followers_count":772788,"friends_count":1760,"listed_count":8089,"created_at":"Fri Oct 17 14:36:15 +0000 2008","favourites_count":16866,"utc_offset":-18000,"time_zone":"Eastern Time (US & Canada)","geo_enabled":true,"verified":true,"statuses_count":37494,"lang":"en","contributors_enabled":false,"is_translator":false,"is_translation_enabled":false,"profile_background_color":"050505","profile_background_image_url":"http://pbs.twimg.com/profile_background_images/476097608331456514/7_-kDrVg.jpeg","profile_background_image_url_https":"https://pbs.twimg.com/profile_background_images/476097608331456514/7_-kDrVg.jpeg","profile_background_tile":true,"profile_image_url":"http://pbs.twimg.com/profile_images/423212466315603968/rg7S67U3_normal.png","profile_image_url_https":"https://pbs.twimg.com/profile_images/423212466315603968/rg7S67U3_normal.png","profile_banner_url":"https://pbs.twimg.com/profile_banners/16825289/1415201289","profile_link_color":"009999","profile_sidebar_border_color":"000000","profile_sidebar_fill_color":"EBEBEB","profile_text_color":"454545","profile_use_background_image":true,"default_profile":false,"default_profile_image":false,"following":false,"follow_request_sent":false,"notifications":false},{"id":7846,"id_str":"7846","name":"Justine Ezarik","screen_name":"ijustine","location":"Los Angeles, CA","profile_location":null,"description":"I make stuff on the internet!","url":"http://t.co/Mz4wcCK2hS","entities":{"url":{"urls":[{"url":"http://t.co/Mz4wcCK2hS","expanded_url":"http://youtube.com/ijustine","display_url":"youtube.com/ijustine","indices":[0,22]}]},"description":{"urls":[]}},"protected":false,"followers_count":1727485,"friends_count":4812,"listed_count":15503,"created_at":"Tue Oct 10 02:53:00 +0000 2006","favourites_count":823,"utc_offset":-28800,"time_zone":"Pacific Time (US & Canada)","geo_enabled":false,"verified":true,"statuses_count":27944,"lang":"en","contributors_enabled":false,"is_translator":false,"is_translation_enabled":false,"profile_background_color":"DBDBDB","profile_background_image_url":"http://abs.twimg.com/images/themes/theme14/bg.gif","profile_background_image_url_https":"https://abs.twimg.com/images/themes/theme14/bg.gif","profile_background_tile":false,"profile_image_url":"http://pbs.twimg.com/profile_images/501081312279556096/yrQ7ccO-_normal.jpeg","profile_image_url_https":"https://pbs.twimg.com/profile_images/501081312279556096/yrQ7ccO-_normal.jpeg","profile_banner_url":"https://pbs.twimg.com/profile_banners/7846/1408301323","profile_link_color":"BD89F5","profile_sidebar_border_color":"000000","profile_sidebar_fill_color":"EFEFEF","profile_text_color":"333333","profile_use_background_image":false,"default_profile":false,"default_profile_image":false,"following":false,"follow_request_sent":false,"notifications":false},{"id":1259785938,"id_str":"1259785938","name":"Superfight","screen_name":"Superfight","location":"","profile_location":null,"description":"A game of absurd arguments. Check out: http://t.co/RHpFrY0Kkx! Created by @luckyshirt and produced by @Skybound.","url":"http://t.co/6fo5VBqUqs","entities":{"url":{"urls":[{"url":"http://t.co/6fo5VBqUqs","expanded_url":"http://SuperfightGame.com","display_url":"SuperfightGame.com","indices":[0,22]}]},"description":{"urls":[{"url":"http://t.co/RHpFrY0Kkx","expanded_url":"http://www.SuperfightGame.com","display_url":"SuperfightGame.com","indices":[39,61]}]}},"protected":false,"followers_count":19846,"friends_count":317,"listed_count":18,"created_at":"Mon Mar 11 16:02:19 +0000 2013","favourites_count":242,"utc_offset":-25200,"time_zone":"Arizona","geo_enabled":false,"verified":false,"statuses_count":376,"lang":"en","contributors_enabled":false,"is_translator":false,"is_translation_enabled":false,"profile_background_color":"131516","profile_background_image_url":"http://abs.twimg.com/images/themes/theme14/bg.gif","profile_background_image_url_https":"https://abs.twimg.com/images/themes/theme14/bg.gif","profile_background_tile":true,"profile_image_url":"http://pbs.twimg.com/profile_images/429037870989336576/AZDn3b9J_normal.png","profile_image_url_https":"https://pbs.twimg.com/profile_images/429037870989336576/AZDn3b9J_normal.png","profile_banner_url":"https://pbs.twimg.com/profile_banners/1259785938/1390935983","profile_link_color":"009999","profile_sidebar_border_color":"EEEEEE","profile_sidebar_fill_color":"EFEFEF","profile_text_color":"333333","profile_use_background_image":true,"default_profile":false,"default_profile_image":false,"following":false,"follow_request_sent":false,"notifications":false},{"id":19542638,"id_str":"19542638","name":"Lisa Lampanelli","screen_name":"LisaLampanelli","location":"New York City","profile_location":null,"description":"Comedy's Lovable Queen of Mean, standup comedian, actress, equal opportunity offender","url":"http://t.co/jcco2EzIpM","entities":{"url":{"urls":[{"url":"http://t.co/jcco2EzIpM","expanded_url":"http://www.InsultComic.com","display_url":"InsultComic.com","indices":[0,22]}]},"description":{"urls":[]}},"protected":false,"followers_count":554872,"friends_count":13810,"listed_count":6218,"created_at":"Mon Jan 26 16:34:16 +0000 2009","favourites_count":10,"utc_offset":-18000,"time_zone":"Eastern Time (US & Canada)","geo_enabled":false,"verified":true,"statuses_count":12509,"lang":"en","contributors_enabled":false,"is_translator":false,"is_translation_enabled":false,"profile_background_color":"030000","profile_background_image_url":"http://pbs.twimg.com/profile_background_images/438363466223472640/69at3ch4.jpeg","profile_background_image_url_https":"https://pbs.twimg.com/profile_background_images/438363466223472640/69at3ch4.jpeg","profile_background_tile":false,"profile_image_url":"http://pbs.twimg.com/profile_images/438481906850463744/K7_QpmWS_normal.jpeg","profile_image_url_https":"https://pbs.twimg.com/profile_images/438481906850463744/K7_QpmWS_normal.jpeg","profile_banner_url":"https://pbs.twimg.com/profile_banners/19542638/1393377196","profile_link_color":"030001","profile_sidebar_border_color":"FFFFFF","profile_sidebar_fill_color":"DFDDD1","profile_text_color":"000000","profile_use_background_image":true,"default_profile":false,"default_profile_image":false,"following":false,"follow_request_sent":false,"notifications":false},{"id":46233559,"id_str":"46233559","name":"rose mcgowan","screen_name":"rosemcgowan","location":"Los Angeles, CA","profile_location":null,"description":"Rose McGowan \nDirector/Actress\nInstagram: @rosemcgowan \ntumblr @rosemcgowan\nfacebook rosemcgowan \nreal life me","url":null,"entities":{"description":{"urls":[]}},"protected":false,"followers_count":538308,"friends_count":519,"listed_count":7625,"created_at":"Wed Jun 10 21:39:32 +0000 2009","favourites_count":42,"utc_offset":-28800,"time_zone":"Pacific Time (US & Canada)","geo_enabled":false,"verified":true,"statuses_count":8264,"lang":"en","contributors_enabled":false,"is_translator":false,"is_translation_enabled":false,"profile_background_color":"DBE9ED","profile_background_image_url":"http://abs.twimg.com/images/themes/theme17/bg.gif","profile_background_image_url_https":"https://abs.twimg.com/images/themes/theme17/bg.gif","profile_background_tile":false,"profile_image_url":"http://pbs.twimg.com/profile_images/519396957500870656/3ZoBH44g_normal.jpeg","profile_image_url_https":"https://pbs.twimg.com/profile_images/519396957500870656/3ZoBH44g_normal.jpeg","profile_banner_url":"https://pbs.twimg.com/profile_banners/46233559/1412294079","profile_link_color":"CC3366","profile_sidebar_border_color":"DBE9ED","profile_sidebar_fill_color":"E6F6F9","profile_text_color":"333333","profile_use_background_image":true,"default_profile":false,"default_profile_image":false,"following":false,"follow_request_sent":false,"notifications":false},{"id":121887978,"id_str":"121887978","name":"Noor Al Hussein","screen_name":"QueenNoor","location":"global @KHF_NHF","profile_location":null,"description":"faithful child of Abraham, idealistic global citizen/public servant in perpetual motion and proud mother;author:'Leap of Faith'","url":"http://t.co/7Muk5xeDEE","entities":{"url":{"urls":[{"url":"http://t.co/7Muk5xeDEE","expanded_url":"http://www.kinghusseinfoundation.org","display_url":"kinghusseinfoundation.org","indices":[0,22]}]},"description":{"urls":[]}},"protected":false,"followers_count":431914,"friends_count":306,"listed_count":2893,"created_at":"Wed Mar 10 23:00:31 +0000 2010","favourites_count":44,"utc_offset":-21600,"time_zone":"Central Time (US & Canada)","geo_enabled":false,"verified":true,"statuses_count":3341,"lang":"en","contributors_enabled":false,"is_translator":false,"is_translation_enabled":false,"profile_background_color":"642D8B","profile_background_image_url":"http://abs.twimg.com/images/themes/theme10/bg.gif","profile_background_image_url_https":"https://abs.twimg.com/images/themes/theme10/bg.gif","profile_background_tile":true,"profile_image_url":"http://pbs.twimg.com/profile_images/1325463564/image_normal.jpg","profile_image_url_https":"https://pbs.twimg.com/profile_images/1325463564/image_normal.jpg","profile_link_color":"FF0000","profile_sidebar_border_color":"65B0DA","profile_sidebar_fill_color":"7AC3EE","profile_text_color":"3D1957","profile_use_background_image":true,"default_profile":false,"default_profile_image":false,"following":false,"follow_request_sent":false,"notifications":false},{"id":10798802,"id_str":"10798802","name":"Amanda Palmer","screen_name":"amandapalmer","location":"boston/NYC/melbourne/the road","profile_location":null,"description":"performer, writer, giver, taker, yeller, listener, love-lover, rule-hater…my book “THE ART OF ASKING” is out on 11/11. preorder signed hardcovers from my site.","url":"http://t.co/8VQ1FixlVW","entities":{"url":{"urls":[{"url":"http://t.co/8VQ1FixlVW","expanded_url":"http://bit.ly/AFPweb","display_url":"bit.ly/AFPweb","indices":[0,22]}]},"description":{"urls":[]}},"protected":false,"followers_count":1047573,"friends_count":484,"listed_count":11139,"created_at":"Mon Dec 03 01:27:35 +0000 2007","favourites_count":104,"utc_offset":-18000,"time_zone":"Eastern Time (US & Canada)","geo_enabled":false,"verified":true,"statuses_count":69152,"lang":"en","contributors_enabled":false,"is_translator":false,"is_translation_enabled":false,"profile_background_color":"DB2B1F","profile_background_image_url":"http://pbs.twimg.com/profile_background_images/512714703240310785/-2tP8Hsw.jpeg","profile_background_image_url_https":"https://pbs.twimg.com/profile_background_images/512714703240310785/-2tP8Hsw.jpeg","profile_background_tile":true,"profile_image_url":"http://pbs.twimg.com/profile_images/510069541200617473/OiX5QHDB_normal.jpeg","profile_image_url_https":"https://pbs.twimg.com/profile_images/510069541200617473/OiX5QHDB_normal.jpeg","profile_banner_url":"https://pbs.twimg.com/profile_banners/10798802/1411164317","profile_link_color":"1A184D","profile_sidebar_border_color":"FFFFFF","profile_sidebar_fill_color":"FFA9A9","profile_text_color":"493636","profile_use_background_image":true,"default_profile":false,"default_profile_image":false,"following":false,"follow_request_sent":false,"notifications":false},{"id":17298532,"id_str":"17298532","name":"Only in SF","screen_name":"onlyinsf","location":"San Francisco, CA","profile_location":null,"description":"Official visitor information for San Francisco. How may we help you enjoy your stay? Contact Us: http://t.co/jhiPQ8K3Mn","url":"http://t.co/u0wCmV6QW8","entities":{"url":{"urls":[{"url":"http://t.co/u0wCmV6QW8","expanded_url":"http://www.sanfrancisco.travel","display_url":"sanfrancisco.travel","indices":[0,22]}]},"description":{"urls":[{"url":"http://t.co/jhiPQ8K3Mn","expanded_url":"http://bit.ly/ofle7o","display_url":"bit.ly/ofle7o","indices":[97,119]}]}},"protected":false,"followers_count":145395,"friends_count":1721,"listed_count":2185,"created_at":"Tue Nov 11 00:02:06 +0000 2008","favourites_count":357,"utc_offset":-32400,"time_zone":"Alaska","geo_enabled":false,"verified":true,"statuses_count":7155,"lang":"en","contributors_enabled":false,"is_translator":false,"is_translation_enabled":false,"profile_background_color":"E7EBEC","profile_background_image_url":"http://pbs.twimg.com/profile_background_images/17683546/shutterstock_28634767.jpg","profile_background_image_url_https":"https://pbs.twimg.com/profile_background_images/17683546/shutterstock_28634767.jpg","profile_background_tile":false,"profile_image_url":"http://pbs.twimg.com/profile_images/968796434/iStock_000009193881XLarge_normal.jpg","profile_image_url_https":"https://pbs.twimg.com/profile_images/968796434/iStock_000009193881XLarge_normal.jpg","profile_banner_url":"https://pbs.twimg.com/profile_banners/17298532/1379973352","profile_link_color":"BD3632","profile_sidebar_border_color":"96B3BB","profile_sidebar_fill_color":"A1C6CF","profile_text_color":"333333","profile_use_background_image":true,"default_profile":false,"default_profile_image":false,"following":false,"follow_request_sent":false,"notifications":false},{"id":6480652,"id_str":"6480652","name":"Paul Scheer","screen_name":"paulscheer","location":"Los Angeles, CA","profile_location":null,"description":"Uses Furniture but Doesn't Trust it.","url":"http://t.co/0bWyf0cbIO","entities":{"url":{"urls":[{"url":"http://t.co/0bWyf0cbIO","expanded_url":"http://www.paulscheer.com","display_url":"paulscheer.com","indices":[0,22]}]},"description":{"urls":[]}},"protected":false,"followers_count":659129,"friends_count":1214,"listed_count":6995,"created_at":"Thu May 31 19:05:17 +0000 2007","favourites_count":4783,"utc_offset":-28800,"time_zone":"Pacific Time (US & Canada)","geo_enabled":false,"verified":true,"statuses_count":5149,"lang":"en","contributors_enabled":false,"is_translator":false,"is_translation_enabled":false,"profile_background_color":"53A1E6","profile_background_image_url":"http://pbs.twimg.com/profile_background_images/499071899591122944/HgMrQVt7.jpeg","profile_background_image_url_https":"https://pbs.twimg.com/profile_background_images/499071899591122944/HgMrQVt7.jpeg","profile_background_tile":false,"profile_image_url":"http://pbs.twimg.com/profile_images/501591202341195777/y9TThaVc_normal.jpeg","profile_image_url_https":"https://pbs.twimg.com/profile_images/501591202341195777/y9TThaVc_normal.jpeg","profile_banner_url":"https://pbs.twimg.com/profile_banners/6480652/1415212300","profile_link_color":"2FC2EF","profile_sidebar_border_color":"000000","profile_sidebar_fill_color":"252429","profile_text_color":"666666","profile_use_background_image":true,"default_profile":false,"default_profile_image":false,"following":false,"follow_request_sent":false,"notifications":false},{"id":774096,"id_str":"774096","name":"Cali Lewis","screen_name":"CaliLewis","location":"Dallas, TX","profile_location":null,"description":"Professional Geek. Host of GeekBeat.TV. Tech Expert for ABC/CNN/FOX/SiriusXM. Speaker. Inspiring others to embrace their inner geek! And of course, bacon.","url":"http://t.co/o2c0dqpvsI","entities":{"url":{"urls":[{"url":"http://t.co/o2c0dqpvsI","expanded_url":"http://google.com/+calilewis","display_url":"google.com/+calilewis","indices":[0,22]}]},"description":{"urls":[]}},"protected":false,"followers_count":217782,"friends_count":955,"listed_count":9789,"created_at":"Thu Feb 15 17:24:00 +0000 2007","favourites_count":146,"utc_offset":null,"time_zone":null,"geo_enabled":true,"verified":true,"statuses_count":16523,"lang":"en","contributors_enabled":false,"is_translator":false,"is_translation_enabled":false,"profile_background_color":"1F1F1F","profile_background_image_url":"http://pbs.twimg.com/profile_background_images/116623209/twitter-background_Cali.jpg","profile_background_image_url_https":"https://pbs.twimg.com/profile_background_images/116623209/twitter-background_Cali.jpg","profile_background_tile":false,"profile_image_url":"http://pbs.twimg.com/profile_images/3604942165/c627f87223f01f7e7e1293b8ef70cafd_normal.jpeg","profile_image_url_https":"https://pbs.twimg.com/profile_images/3604942165/c627f87223f01f7e7e1293b8ef70cafd_normal.jpeg","profile_banner_url":"https://pbs.twimg.com/profile_banners/774096/1401714317","profile_link_color":"2E82FF","profile_sidebar_border_color":"000000","profile_sidebar_fill_color":"636363","profile_text_color":"000000","profile_use_background_image":true,"default_profile":false,"default_profile_image":false,"following":false,"follow_request_sent":false,"notifications":false},{"id":15661871,"id_str":"15661871","name":"Adam Savage","screen_name":"donttrythis","location":"San Francisco","profile_location":null,"description":"I play a scientist on TV. Obsessive maker of things. Host of Mythbusters on the Discovery Channel.","url":"http://t.co/Nf0dXrGKlC","entities":{"url":{"urls":[{"url":"http://t.co/Nf0dXrGKlC","expanded_url":"http://www.tested.com","display_url":"tested.com","indices":[0,22]}]},"description":{"urls":[]}},"protected":false,"followers_count":1180840,"friends_count":291,"listed_count":23442,"created_at":"Wed Jul 30 15:55:46 +0000 2008","favourites_count":298,"utc_offset":-28800,"time_zone":"Pacific Time (US & Canada)","geo_enabled":false,"verified":true,"statuses_count":8686,"lang":"en","contributors_enabled":false,"is_translator":false,"is_translation_enabled":false,"profile_background_color":"2F3333","profile_background_image_url":"http://pbs.twimg.com/profile_background_images/378800000163126575/Ywnj1ruy.jpeg","profile_background_image_url_https":"https://pbs.twimg.com/profile_background_images/378800000163126575/Ywnj1ruy.jpeg","profile_background_tile":false,"profile_image_url":"http://pbs.twimg.com/profile_images/458749057985282048/cre48Dcf_normal.jpeg","profile_image_url_https":"https://pbs.twimg.com/profile_images/458749057985282048/cre48Dcf_normal.jpeg","profile_banner_url":"https://pbs.twimg.com/profile_banners/15661871/1414089747","profile_link_color":"FF3300","profile_sidebar_border_color":"000000","profile_sidebar_fill_color":"A0C5C7","profile_text_color":"333333","profile_use_background_image":true,"default_profile":false,"default_profile_image":false,"following":false,"follow_request_sent":false,"notifications":false},{"id":14137737,"id_str":"14137737","name":"Anthony Carboni","screen_name":"acarboni","location":"Los Angeles, CA","profile_location":null,"description":"Host/writer. My new show: http://t.co/9c0mv4G1Yo Previously: @DNews, @NatureHates, @Rev3Games.","url":"http://t.co/1oCx3TY35Z","entities":{"url":{"urls":[{"url":"http://t.co/1oCx3TY35Z","expanded_url":"http://www.anthonycarboni.com","display_url":"anthonycarboni.com","indices":[0,22]}]},"description":{"urls":[{"url":"http://t.co/9c0mv4G1Yo","expanded_url":"http://wehaveconcerns.com","display_url":"wehaveconcerns.com","indices":[26,48]}]}},"protected":false,"followers_count":49227,"friends_count":803,"listed_count":725,"created_at":"Thu Mar 13 05:34:25 +0000 2008","favourites_count":4110,"utc_offset":-28800,"time_zone":"Pacific Time (US & Canada)","geo_enabled":false,"verified":false,"statuses_count":30673,"lang":"en","contributors_enabled":false,"is_translator":false,"is_translation_enabled":false,"profile_background_color":"181B29","profile_background_image_url":"http://pbs.twimg.com/profile_background_images/3014378/twitterbridge.jpg","profile_background_image_url_https":"https://pbs.twimg.com/profile_background_images/3014378/twitterbridge.jpg","profile_background_tile":false,"profile_image_url":"http://pbs.twimg.com/profile_images/508054390239158272/BzIv8zQD_normal.jpeg","profile_image_url_https":"https://pbs.twimg.com/profile_images/508054390239158272/BzIv8zQD_normal.jpeg","profile_banner_url":"https://pbs.twimg.com/profile_banners/14137737/1347995310","profile_link_color":"0000FF","profile_sidebar_border_color":"FFFFFF","profile_sidebar_fill_color":"E0FF92","profile_text_color":"000000","profile_use_background_image":false,"default_profile":false,"default_profile_image":false,"following":false,"follow_request_sent":false,"notifications":false},{"id":14321959,"id_str":"14321959","name":"umair ","screen_name":"umairh","location":"london/paris/nyc","profile_location":null,"description":"author, dreamer, everyone's bff.","url":"http://t.co/mYVv0jwa7R","entities":{"url":{"urls":[{"url":"http://t.co/mYVv0jwa7R","expanded_url":"http://www.umairhaque.com/?view=flipcard","display_url":"umairhaque.com/?view=flipcard","indices":[0,22]}]},"description":{"urls":[]}},"protected":false,"followers_count":229649,"friends_count":1164,"listed_count":6391,"created_at":"Mon Apr 07 11:32:29 +0000 2008","favourites_count":382,"utc_offset":-36000,"time_zone":"Hawaii","geo_enabled":false,"verified":true,"statuses_count":69466,"lang":"en","contributors_enabled":false,"is_translator":false,"is_translation_enabled":false,"profile_background_color":"C0DEED","profile_background_image_url":"http://abs.twimg.com/images/themes/theme1/bg.png","profile_background_image_url_https":"https://abs.twimg.com/images/themes/theme1/bg.png","profile_background_tile":false,"profile_image_url":"http://pbs.twimg.com/profile_images/427316127916494848/idsuKJeo_normal.jpeg","profile_image_url_https":"https://pbs.twimg.com/profile_images/427316127916494848/idsuKJeo_normal.jpeg","profile_link_color":"0084B4","profile_sidebar_border_color":"C0DEED","profile_sidebar_fill_color":"DDEEF6","profile_text_color":"333333","profile_use_background_image":true,"default_profile":true,"default_profile_image":false,"following":false,"follow_request_sent":false,"notifications":false},{"id":15060582,"id_str":"15060582","name":"Darin Ross","screen_name":"luckyshirt","location":"Los Angeles","profile_location":null,"description":"Creator of Superfight and Find the Starlight. I also write a lot about being a single dad. But to most people, I'm just the guy who wrote the burrito rant.","url":"https://t.co/2OkY0B03zb","entities":{"url":{"urls":[{"url":"https://t.co/2OkY0B03zb","expanded_url":"https://medium.com/p/fd08c0babb57#01af-1b8e61ada3c5","display_url":"medium.com/p/fd08c0babb57…","indices":[0,23]}]},"description":{"urls":[]}},"protected":false,"followers_count":63146,"friends_count":859,"listed_count":1513,"created_at":"Mon Jun 09 15:40:32 +0000 2008","favourites_count":20268,"utc_offset":-18000,"time_zone":"Quito","geo_enabled":false,"verified":false,"statuses_count":678,"lang":"en","contributors_enabled":false,"is_translator":false,"is_translation_enabled":false,"profile_background_color":"EDECE9","profile_background_image_url":"http://pbs.twimg.com/profile_background_images/567728523/3uypbgi7cmiwvty3fg4y.jpeg","profile_background_image_url_https":"https://pbs.twimg.com/profile_background_images/567728523/3uypbgi7cmiwvty3fg4y.jpeg","profile_background_tile":false,"profile_image_url":"http://pbs.twimg.com/profile_images/508072389410697217/BIbWpE2K_normal.jpeg","profile_image_url_https":"https://pbs.twimg.com/profile_images/508072389410697217/BIbWpE2K_normal.jpeg","profile_banner_url":"https://pbs.twimg.com/profile_banners/15060582/1409147449","profile_link_color":"DB091A","profile_sidebar_border_color":"CC3366","profile_sidebar_fill_color":"E5507E","profile_text_color":"362720","profile_use_background_image":false,"default_profile":false,"default_profile_image":false,"following":false,"follow_request_sent":false,"notifications":false},{"id":17945384,"id_str":"17945384","name":"Geographer","screen_name":"geographermusic","location":"San Francisco","profile_location":null,"description":"Indie-rock trio from San Francisco, CA.","url":"http://t.co/baJHLMT0T7","entities":{"url":{"urls":[{"url":"http://t.co/baJHLMT0T7","expanded_url":"http://www.geographermusic.com","display_url":"geographermusic.com","indices":[0,22]}]},"description":{"urls":[]}},"protected":false,"followers_count":62357,"friends_count":508,"listed_count":329,"created_at":"Sun Dec 07 18:41:41 +0000 2008","favourites_count":4205,"utc_offset":-28800,"time_zone":"Pacific Time (US & Canada)","geo_enabled":true,"verified":true,"statuses_count":4855,"lang":"en","contributors_enabled":false,"is_translator":false,"is_translation_enabled":false,"profile_background_color":"9AE4E8","profile_background_image_url":"http://pbs.twimg.com/profile_background_images/386125176/Geographer_Twitter_Background_FINAL.jpg","profile_background_image_url_https":"https://pbs.twimg.com/profile_background_images/386125176/Geographer_Twitter_Background_FINAL.jpg","profile_background_tile":false,"profile_image_url":"http://pbs.twimg.com/profile_images/378800000021963587/e32fa410f109436f29afe654714c60ad_normal.jpeg","profile_image_url_https":"https://pbs.twimg.com/profile_images/378800000021963587/e32fa410f109436f29afe654714c60ad_normal.jpeg","profile_banner_url":"https://pbs.twimg.com/profile_banners/17945384/1388687838","profile_link_color":"1B9DD4","profile_sidebar_border_color":"BDDCAD","profile_sidebar_fill_color":"DDFFCC","profile_text_color":"333333","profile_use_background_image":true,"default_profile":false,"default_profile_image":false,"following":false,"follow_request_sent":false,"notifications":false},{"id":18619979,"id_str":"18619979","name":"Maria Kochetkova","screen_name":"balletrusse","location":"San Francisco","profile_location":null,"description":"Principal Dancer with San Francisco Ballet. Guest with Mariinsky, Bolshoi and Tokyo Ballets. Former dancer with English National Ballet and Royal Ballet.","url":"http://t.co/RubsiQD5lM","entities":{"url":{"urls":[{"url":"http://t.co/RubsiQD5lM","expanded_url":"http://mariakochetkova.com","display_url":"mariakochetkova.com","indices":[0,22]}]},"description":{"urls":[]}},"protected":false,"followers_count":203009,"friends_count":1136,"listed_count":1532,"created_at":"Mon Jan 05 02:04:53 +0000 2009","favourites_count":1157,"utc_offset":-28800,"time_zone":"Pacific Time (US & Canada)","geo_enabled":true,"verified":true,"statuses_count":3908,"lang":"en","contributors_enabled":false,"is_translator":false,"is_translation_enabled":false,"profile_background_color":"DBC7C9","profile_background_image_url":"http://pbs.twimg.com/profile_background_images/85254626/maria-kochetkova-pointe.png","profile_background_image_url_https":"https://pbs.twimg.com/profile_background_images/85254626/maria-kochetkova-pointe.png","profile_background_tile":true,"profile_image_url":"http://pbs.twimg.com/profile_images/2830531361/3bbe997a3f27fa1dc808835f45156412_normal.jpeg","profile_image_url_https":"https://pbs.twimg.com/profile_images/2830531361/3bbe997a3f27fa1dc808835f45156412_normal.jpeg","profile_banner_url":"https://pbs.twimg.com/profile_banners/18619979/1357062592","profile_link_color":"CD046C","profile_sidebar_border_color":"9489B2","profile_sidebar_fill_color":"F8D7D7","profile_text_color":"333333","profile_use_background_image":true,"default_profile":false,"default_profile_image":false,"following":false,"follow_request_sent":false,"notifications":false},{"id":18958606,"id_str":"18958606","name":"blurbinc","screen_name":"BlurbBooks","location":"San Francisco, CA","profile_location":null,"description":"Blurb® helps you tell and share your stories: in bookstore-quality books, on the web, and with your mobile. Your genius, our tools.","url":"http://t.co/MEa6BDEQEK","entities":{"url":{"urls":[{"url":"http://t.co/MEa6BDEQEK","expanded_url":"http://blurb.com","display_url":"blurb.com","indices":[0,22]}]},"description":{"urls":[]}},"protected":false,"followers_count":110693,"friends_count":1573,"listed_count":2103,"created_at":"Tue Jan 13 23:32:55 +0000 2009","favourites_count":388,"utc_offset":-32400,"time_zone":"Alaska","geo_enabled":true,"verified":true,"statuses_count":11224,"lang":"en","contributors_enabled":false,"is_translator":false,"is_translation_enabled":false,"profile_background_color":"FFFFFF","profile_background_image_url":"http://pbs.twimg.com/profile_background_images/838662321/1bdf656fa75f3d337c7a0202aefbcbb0.png","profile_background_image_url_https":"https://pbs.twimg.com/profile_background_images/838662321/1bdf656fa75f3d337c7a0202aefbcbb0.png","profile_background_tile":false,"profile_image_url":"http://pbs.twimg.com/profile_images/461586757524275200/m_h5S-gs_normal.jpeg","profile_image_url_https":"https://pbs.twimg.com/profile_images/461586757524275200/m_h5S-gs_normal.jpeg","profile_banner_url":"https://pbs.twimg.com/profile_banners/18958606/1398885822","profile_link_color":"00ABEF","profile_sidebar_border_color":"FFFFFF","profile_sidebar_fill_color":"FFFFFF","profile_text_color":"666666","profile_use_background_image":true,"default_profile":false,"default_profile_image":false,"following":false,"follow_request_sent":false,"notifications":false},{"id":301738604,"id_str":"301738604","name":"Jeremy Fish","screen_name":"JeremyFish","location":"SAN FRANFISHCO","profile_location":null,"description":"http://t.co/UTLXRtQIpP","url":"http://t.co/qflCDWnCrg","entities":{"url":{"urls":[{"url":"http://t.co/qflCDWnCrg","expanded_url":"http://jeremyfish.wordpress.com","display_url":"jeremyfish.wordpress.com","indices":[0,22]}]},"description":{"urls":[{"url":"http://t.co/UTLXRtQIpP","expanded_url":"http://sillypinkbunnies.com","display_url":"sillypinkbunnies.com","indices":[0,22]}]}},"protected":false,"followers_count":56957,"friends_count":101,"listed_count":212,"created_at":"Fri May 20 00:01:02 +0000 2011","favourites_count":1069,"utc_offset":-28800,"time_zone":"Pacific Time (US & Canada)","geo_enabled":true,"verified":false,"statuses_count":1971,"lang":"en","contributors_enabled":false,"is_translator":false,"is_translation_enabled":false,"profile_background_color":"4A2708","profile_background_image_url":"http://abs.twimg.com/images/themes/theme1/bg.png","profile_background_image_url_https":"https://abs.twimg.com/images/themes/theme1/bg.png","profile_background_tile":false,"profile_image_url":"http://pbs.twimg.com/profile_images/1361572604/TWITTER_ICON_normal.jpg","profile_image_url_https":"https://pbs.twimg.com/profile_images/1361572604/TWITTER_ICON_normal.jpg","profile_link_color":"701F07","profile_sidebar_border_color":"FCFCFC","profile_sidebar_fill_color":"C26D06","profile_text_color":"0A010A","profile_use_background_image":false,"default_profile":false,"default_profile_image":false,"following":false,"follow_request_sent":false,"notifications":false},{"id":17372853,"id_str":"17372853","name":"Honor Society","screen_name":"honorsociety","location":"A Tale of Risky Business...","profile_location":null,"description":"","url":null,"entities":{"description":{"urls":[]}},"protected":false,"followers_count":153932,"friends_count":22542,"listed_count":2914,"created_at":"Thu Nov 13 21:17:24 +0000 2008","favourites_count":44,"utc_offset":-28800,"time_zone":"Pacific Time (US & Canada)","geo_enabled":false,"verified":true,"statuses_count":7669,"lang":"en","contributors_enabled":false,"is_translator":false,"is_translation_enabled":false,"profile_background_color":"FFFFFF","profile_background_image_url":"http://abs.twimg.com/images/themes/theme14/bg.gif","profile_background_image_url_https":"https://abs.twimg.com/images/themes/theme14/bg.gif","profile_background_tile":true,"profile_image_url":"http://pbs.twimg.com/profile_images/3565793763/51f9bf72468180181530d1665e111c75_normal.jpeg","profile_image_url_https":"https://pbs.twimg.com/profile_images/3565793763/51f9bf72468180181530d1665e111c75_normal.jpeg","profile_banner_url":"https://pbs.twimg.com/profile_banners/17372853/1366746946","profile_link_color":"009999","profile_sidebar_border_color":"FFFFFF","profile_sidebar_fill_color":"EFEFEF","profile_text_color":"333333","profile_use_background_image":false,"default_profile":false,"default_profile_image":false,"following":false,"follow_request_sent":false,"notifications":false},{"id":20592647,"id_str":"20592647","name":"DΞLUKΔ","screen_name":"deluka","location":"Birmingham, UK to └A","profile_location":null,"description":"Download our new Bonds EP iTunes: http://t.co/cwnNR5CU9X. #BondsEP","url":"http://t.co/NJLQp7vKER","entities":{"url":{"urls":[{"url":"http://t.co/NJLQp7vKER","expanded_url":"http://www.deluka.com","display_url":"deluka.com","indices":[0,22]}]},"description":{"urls":[{"url":"http://t.co/cwnNR5CU9X","expanded_url":"http://smarturl.it/BondsEP?IQid=twitter","display_url":"smarturl.it/BondsEP?IQid=t…","indices":[34,56]}]}},"protected":false,"followers_count":45966,"friends_count":520,"listed_count":179,"created_at":"Wed Feb 11 14:23:35 +0000 2009","favourites_count":1383,"utc_offset":0,"time_zone":"London","geo_enabled":true,"verified":true,"statuses_count":5484,"lang":"en","contributors_enabled":false,"is_translator":false,"is_translation_enabled":false,"profile_background_color":"000000","profile_background_image_url":"http://pbs.twimg.com/profile_background_images/378800000177189671/CeHxLeON.jpeg","profile_background_image_url_https":"https://pbs.twimg.com/profile_background_images/378800000177189671/CeHxLeON.jpeg","profile_background_tile":true,"profile_image_url":"http://pbs.twimg.com/profile_images/427857588441473024/iwAgGJBs_normal.jpeg","profile_image_url_https":"https://pbs.twimg.com/profile_images/427857588441473024/iwAgGJBs_normal.jpeg","profile_banner_url":"https://pbs.twimg.com/profile_banners/20592647/1409767107","profile_link_color":"555555","profile_sidebar_border_color":"FFFFFF","profile_sidebar_fill_color":"FFFFFF","profile_text_color":"333333","profile_use_background_image":true,"default_profile":false,"default_profile_image":false,"following":false,"follow_request_sent":false,"notifications":false},{"id":20745130,"id_str":"20745130","name":"Zach Weinersmummy","screen_name":"ZachWeiner","location":"","profile_location":null,"description":"His comics are the very best, Credo quia absurdum est\r\n\r\nMarried to @fuschmu\r\n\r\n(Support SMBC at http://t.co/eJVenroutf)","url":"http://t.co/PN8Jbo9IoI","entities":{"url":{"urls":[{"url":"http://t.co/PN8Jbo9IoI","expanded_url":"http://www.smbc-comics.com","display_url":"smbc-comics.com","indices":[0,22]}]},"description":{"urls":[{"url":"http://t.co/eJVenroutf","expanded_url":"http://patreon.com/zachweinersmith/","display_url":"patreon.com/zachweinersmit…","indices":[97,119]}]}},"protected":false,"followers_count":88509,"friends_count":1315,"listed_count":1819,"created_at":"Fri Feb 13 03:38:35 +0000 2009","favourites_count":2161,"utc_offset":-21600,"time_zone":"Central Time (US & Canada)","geo_enabled":false,"verified":true,"statuses_count":24381,"lang":"en","contributors_enabled":false,"is_translator":false,"is_translation_enabled":false,"profile_background_color":"C0DEED","profile_background_image_url":"http://abs.twimg.com/images/themes/theme1/bg.png","profile_background_image_url_https":"https://abs.twimg.com/images/themes/theme1/bg.png","profile_background_tile":false,"profile_image_url":"http://pbs.twimg.com/profile_images/2634755453/40ffdf8a114b08a13aecc6f2a3a17320_normal.png","profile_image_url_https":"https://pbs.twimg.com/profile_images/2634755453/40ffdf8a114b08a13aecc6f2a3a17320_normal.png","profile_link_color":"0084B4","profile_sidebar_border_color":"C0DEED","profile_sidebar_fill_color":"DDEEF6","profile_text_color":"333333","profile_use_background_image":true,"default_profile":true,"default_profile_image":false,"following":false,"follow_request_sent":false,"notifications":false},{"id":28521141,"id_str":"28521141","name":"Grant Imahara","screen_name":"grantimahara","location":"Los Angeles, CA","profile_location":null,"description":"Robot builder, modelmaker and television host on Mythbusters.","url":"http://t.co/mrxzUGa72y","entities":{"url":{"urls":[{"url":"http://t.co/mrxzUGa72y","expanded_url":"http://grantimahara.com","display_url":"grantimahara.com","indices":[0,22]}]},"description":{"urls":[]}},"protected":false,"followers_count":629140,"friends_count":460,"listed_count":14510,"created_at":"Fri Apr 03 07:05:24 +0000 2009","favourites_count":94,"utc_offset":-28800,"time_zone":"Pacific Time (US & Canada)","geo_enabled":false,"verified":true,"statuses_count":10704,"lang":"en","contributors_enabled":false,"is_translator":false,"is_translation_enabled":false,"profile_background_color":"FFFFFF","profile_background_image_url":"http://pbs.twimg.com/profile_background_images/26401739/twitter-back02.jpg","profile_background_image_url_https":"https://pbs.twimg.com/profile_background_images/26401739/twitter-back02.jpg","profile_background_tile":false,"profile_image_url":"http://pbs.twimg.com/profile_images/378800000781039008/055b00b2c59c19e88e8acb7258342470_normal.jpeg","profile_image_url_https":"https://pbs.twimg.com/profile_images/378800000781039008/055b00b2c59c19e88e8acb7258342470_normal.jpeg","profile_banner_url":"https://pbs.twimg.com/profile_banners/28521141/1402103171","profile_link_color":"30A6F0","profile_sidebar_border_color":"181A1E","profile_sidebar_fill_color":"252429","profile_text_color":"4F4E4F","profile_use_background_image":true,"default_profile":false,"default_profile_image":false,"following":false,"follow_request_sent":false,"notifications":false},{"id":38934368,"id_str":"38934368","name":"matt walsh","screen_name":"mrmattwalsh","location":"Southern California","profile_location":null,"description":"heavy mass star, big fan of cased meats, father, Bears fan, and early adapter of Twitter.","url":"http://t.co/moYMJGZobL","entities":{"url":{"urls":[{"url":"http://t.co/moYMJGZobL","expanded_url":"http://www.facebook.com/pages/Matt-Walsh/198723945343?ref=ts","display_url":"facebook.com/pages/Matt-Wal…","indices":[0,22]}]},"description":{"urls":[]}},"protected":false,"followers_count":106386,"friends_count":297,"listed_count":1272,"created_at":"Sat May 09 21:44:19 +0000 2009","favourites_count":16,"utc_offset":-28800,"time_zone":"Pacific Time (US & Canada)","geo_enabled":false,"verified":true,"statuses_count":5336,"lang":"en","contributors_enabled":false,"is_translator":false,"is_translation_enabled":false,"profile_background_color":"5E5E5E","profile_background_image_url":"http://pbs.twimg.com/profile_background_images/451812204950458368/NVohEvjp.png","profile_background_image_url_https":"https://pbs.twimg.com/profile_background_images/451812204950458368/NVohEvjp.png","profile_background_tile":false,"profile_image_url":"http://pbs.twimg.com/profile_images/451815756364136448/4-MXtEY3_normal.png","profile_image_url_https":"https://pbs.twimg.com/profile_images/451815756364136448/4-MXtEY3_normal.png","profile_banner_url":"https://pbs.twimg.com/profile_banners/38934368/1396555668","profile_link_color":"00991E","profile_sidebar_border_color":"FFFFFF","profile_sidebar_fill_color":"D9D9D9","profile_text_color":"333333","profile_use_background_image":true,"default_profile":false,"default_profile_image":false,"following":false,"follow_request_sent":false,"notifications":false},{"id":54716387,"id_str":"54716387","name":"Owen Benjamin","screen_name":"OwenBenjamin","location":"los angeles","profile_location":null,"description":"big fun pianist","url":"http://t.co/p6nq9Jn42r","entities":{"url":{"urls":[{"url":"http://t.co/p6nq9Jn42r","expanded_url":"http://owenbenjamin.com","display_url":"owenbenjamin.com","indices":[0,22]}]},"description":{"urls":[]}},"protected":false,"followers_count":45703,"friends_count":501,"listed_count":331,"created_at":"Tue Jul 07 23:17:16 +0000 2009","favourites_count":18622,"utc_offset":-28800,"time_zone":"Pacific Time (US & Canada)","geo_enabled":false,"verified":true,"statuses_count":9046,"lang":"en","contributors_enabled":false,"is_translator":false,"is_translation_enabled":false,"profile_background_color":"000000","profile_background_image_url":"http://pbs.twimg.com/profile_background_images/651082093/jgix2483ra3z3exjotjj.jpeg","profile_background_image_url_https":"https://pbs.twimg.com/profile_background_images/651082093/jgix2483ra3z3exjotjj.jpeg","profile_background_tile":false,"profile_image_url":"http://pbs.twimg.com/profile_images/521148875185610753/TCOkfDe0_normal.jpeg","profile_image_url_https":"https://pbs.twimg.com/profile_images/521148875185610753/TCOkfDe0_normal.jpeg","profile_link_color":"0084B4","profile_sidebar_border_color":"EEEEEE","profile_sidebar_fill_color":"EFEFEF","profile_text_color":"333333","profile_use_background_image":true,"default_profile":false,"default_profile_image":false,"following":false,"follow_request_sent":false,"notifications":false},{"id":85259796,"id_str":"85259796","name":"DEVO","screen_name":"DEVO","location":"United States","profile_location":null,"description":"Q: Are We Not Men? A: We Are DEVO!","url":"http://t.co/HSfEaqNZcJ","entities":{"url":{"urls":[{"url":"http://t.co/HSfEaqNZcJ","expanded_url":"http://clubdevo.com","display_url":"clubdevo.com","indices":[0,22]}]},"description":{"urls":[]}},"protected":false,"followers_count":120459,"friends_count":432,"listed_count":1996,"created_at":"Mon Oct 26 07:17:37 +0000 2009","favourites_count":9,"utc_offset":-28800,"time_zone":"Pacific Time (US & Canada)","geo_enabled":false,"verified":true,"statuses_count":2322,"lang":"en","contributors_enabled":false,"is_translator":false,"is_translation_enabled":false,"profile_background_color":"999999","profile_background_image_url":"http://pbs.twimg.com/profile_background_images/606080509/8kcaclf71iqo27d31kzv.jpeg","profile_background_image_url_https":"https://pbs.twimg.com/profile_background_images/606080509/8kcaclf71iqo27d31kzv.jpeg","profile_background_tile":true,"profile_image_url":"http://pbs.twimg.com/profile_images/1826801653/Twitter-RedDome-Logo_normal.jpg","profile_image_url_https":"https://pbs.twimg.com/profile_images/1826801653/Twitter-RedDome-Logo_normal.jpg","profile_banner_url":"https://pbs.twimg.com/profile_banners/85259796/1415107154","profile_link_color":"FF0000","profile_sidebar_border_color":"FFFFFF","profile_sidebar_fill_color":"C7C7C7","profile_text_color":"454545","profile_use_background_image":true,"default_profile":false,"default_profile_image":false,"following":false,"follow_request_sent":false,"notifications":false},{"id":121542666,"id_str":"121542666","name":"M. Tilson Thomas","screen_name":"mtilsonthomas","location":"ÜT: 37.902942,-122.651273","profile_location":null,"description":"Michael Tilson Thomas is @SFSymphony Music Director, @NWSymphony Artistic Director and @LondonSymphony Principal Guest Conductor","url":"http://t.co/DDMi43AJYM","entities":{"url":{"urls":[{"url":"http://t.co/DDMi43AJYM","expanded_url":"http://michaeltilsonthomas.com","display_url":"michaeltilsonthomas.com","indices":[0,22]}]},"description":{"urls":[]}},"protected":false,"followers_count":83612,"friends_count":50,"listed_count":761,"created_at":"Tue Mar 09 20:51:20 +0000 2010","favourites_count":13,"utc_offset":-32400,"time_zone":"Alaska","geo_enabled":true,"verified":true,"statuses_count":555,"lang":"en","contributors_enabled":false,"is_translator":false,"is_translation_enabled":false,"profile_background_color":"022330","profile_background_image_url":"http://abs.twimg.com/images/themes/theme1/bg.png","profile_background_image_url_https":"https://abs.twimg.com/images/themes/theme1/bg.png","profile_background_tile":false,"profile_image_url":"http://pbs.twimg.com/profile_images/743140158/MTT04_small_normal.jpg","profile_image_url_https":"https://pbs.twimg.com/profile_images/743140158/MTT04_small_normal.jpg","profile_banner_url":"https://pbs.twimg.com/profile_banners/121542666/1400095171","profile_link_color":"0084B4","profile_sidebar_border_color":"A8C7F7","profile_sidebar_fill_color":"C0DFEC","profile_text_color":"333333","profile_use_background_image":false,"default_profile":false,"default_profile_image":false,"following":false,"follow_request_sent":false,"notifications":false},{"id":175091719,"id_str":"175091719","name":"Karl the Fog","screen_name":"KarlTheFog","location":"San Francisco, CA","profile_location":null,"description":"All that is sunny does not glitter, not all those in the fog are lost.","url":"http://t.co/iuOLGO95ec","entities":{"url":{"urls":[{"url":"http://t.co/iuOLGO95ec","expanded_url":"http://about.me/karlthefog","display_url":"about.me/karlthefog","indices":[0,22]}]},"description":{"urls":[]}},"protected":false,"followers_count":59218,"friends_count":414,"listed_count":1018,"created_at":"Thu Aug 05 16:27:41 +0000 2010","favourites_count":11078,"utc_offset":-28800,"time_zone":"Pacific Time (US & Canada)","geo_enabled":false,"verified":false,"statuses_count":8382,"lang":"en","contributors_enabled":false,"is_translator":false,"is_translation_enabled":false,"profile_background_color":"131516","profile_background_image_url":"http://abs.twimg.com/images/themes/theme14/bg.gif","profile_background_image_url_https":"https://abs.twimg.com/images/themes/theme14/bg.gif","profile_background_tile":true,"profile_image_url":"http://pbs.twimg.com/profile_images/418790063422459904/_Jvx0ChZ_normal.jpeg","profile_image_url_https":"https://pbs.twimg.com/profile_images/418790063422459904/_Jvx0ChZ_normal.jpeg","profile_banner_url":"https://pbs.twimg.com/profile_banners/175091719/1398197840","profile_link_color":"0A1012","profile_sidebar_border_color":"FFFFFF","profile_sidebar_fill_color":"EFEFEF","profile_text_color":"333333","profile_use_background_image":true,"default_profile":false,"default_profile_image":false,"following":false,"follow_request_sent":false,"notifications":false},{"id":416963802,"id_str":"416963802","name":"Nick Swardson","screen_name":"NickSwardson","location":"","profile_location":null,"description":"Check me out on my 'Taste It' tour this fall on http://t.co/2284jKDj9u","url":"http://t.co/hcaxnoVuyq","entities":{"url":{"urls":[{"url":"http://t.co/hcaxnoVuyq","expanded_url":"http://facebook.com/nickswardsoncomedy","display_url":"facebook.com/nickswardsonco…","indices":[0,22]}]},"description":{"urls":[{"url":"http://t.co/2284jKDj9u","expanded_url":"http://livenation.com","display_url":"livenation.com","indices":[48,70]}]}},"protected":false,"followers_count":565101,"friends_count":438,"listed_count":2407,"created_at":"Sun Nov 20 10:39:15 +0000 2011","favourites_count":4011,"utc_offset":-36000,"time_zone":"Hawaii","geo_enabled":false,"verified":true,"statuses_count":2441,"lang":"en","contributors_enabled":false,"is_translator":false,"is_translation_enabled":false,"profile_background_color":"C0DEED","profile_background_image_url":"http://abs.twimg.com/images/themes/theme1/bg.png","profile_background_image_url_https":"https://abs.twimg.com/images/themes/theme1/bg.png","profile_background_tile":false,"profile_image_url":"http://pbs.twimg.com/profile_images/414586453176246272/7lUKhuHx_normal.jpeg","profile_image_url_https":"https://pbs.twimg.com/profile_images/414586453176246272/7lUKhuHx_normal.jpeg","profile_banner_url":"https://pbs.twimg.com/profile_banners/416963802/1378847952","profile_link_color":"0084B4","profile_sidebar_border_color":"C0DEED","profile_sidebar_fill_color":"DDEEF6","profile_text_color":"333333","profile_use_background_image":true,"default_profile":true,"default_profile_image":false,"following":false,"follow_request_sent":false,"notifications":false},{"id":8067082,"id_str":"8067082","name":"matt","screen_name":"biorhythmist","location":"San Francisco","profile_location":null,"description":"Top Commenter","url":"http://t.co/Xh6pTUMI46","entities":{"url":{"urls":[{"url":"http://t.co/Xh6pTUMI46","expanded_url":"http://about.me/biorhythmist","display_url":"about.me/biorhythmist","indices":[0,22]}]},"description":{"urls":[]}},"protected":false,"followers_count":62334,"friends_count":898,"listed_count":1994,"created_at":"Wed Aug 08 23:33:02 +0000 2007","favourites_count":34423,"utc_offset":-28800,"time_zone":"Pacific Time (US & Canada)","geo_enabled":false,"verified":false,"statuses_count":16644,"lang":"en","contributors_enabled":false,"is_translator":false,"is_translation_enabled":false,"profile_background_color":"9AE4E8","profile_background_image_url":"http://pbs.twimg.com/profile_background_images/164766417/mm.jpg","profile_background_image_url_https":"https://pbs.twimg.com/profile_background_images/164766417/mm.jpg","profile_background_tile":true,"profile_image_url":"http://pbs.twimg.com/profile_images/514104598421061632/SPH3lpkd_normal.jpeg","profile_image_url_https":"https://pbs.twimg.com/profile_images/514104598421061632/SPH3lpkd_normal.jpeg","profile_banner_url":"https://pbs.twimg.com/profile_banners/8067082/1347980662","profile_link_color":"0000FF","profile_sidebar_border_color":"4F5845","profile_sidebar_fill_color":"C8C8C8","profile_text_color":"000000","profile_use_background_image":true,"default_profile":false,"default_profile_image":false,"following":false,"follow_request_sent":false,"notifications":false},{"id":14312841,"id_str":"14312841","name":"kristin hersh","screen_name":"kristinhersh","location":"new england/new orleans ","profile_location":null,"description":"musician, writer, mother of four boys","url":"http://t.co/mHQp38DH7v","entities":{"url":{"urls":[{"url":"http://t.co/mHQp38DH7v","expanded_url":"http://kristinhersh.com","display_url":"kristinhersh.com","indices":[0,22]}]},"description":{"urls":[]}},"protected":false,"followers_count":109399,"friends_count":175,"listed_count":1762,"created_at":"Sat Apr 05 22:32:54 +0000 2008","favourites_count":8053,"utc_offset":-18000,"time_zone":"Eastern Time (US & Canada)","geo_enabled":false,"verified":true,"statuses_count":27322,"lang":"en","contributors_enabled":false,"is_translator":false,"is_translation_enabled":false,"profile_background_color":"EBEBEB","profile_background_image_url":"http://abs.twimg.com/images/themes/theme7/bg.gif","profile_background_image_url_https":"https://abs.twimg.com/images/themes/theme7/bg.gif","profile_background_tile":false,"profile_image_url":"http://pbs.twimg.com/profile_images/2178792646/k_normal.jpg","profile_image_url_https":"https://pbs.twimg.com/profile_images/2178792646/k_normal.jpg","profile_link_color":"990000","profile_sidebar_border_color":"DFDFDF","profile_sidebar_fill_color":"F3F3F3","profile_text_color":"333333","profile_use_background_image":true,"default_profile":false,"default_profile_image":false,"following":false,"follow_request_sent":false,"notifications":false},{"id":14369768,"id_str":"14369768","name":"Mat Johnson","screen_name":"mat_johnson","location":"Absentia","profile_location":null,"description":"Because it amuses me to say so.","url":"http://t.co/UNOzGMXhPz","entities":{"url":{"urls":[{"url":"http://t.co/UNOzGMXhPz","expanded_url":"http://www.matjohnson.info","display_url":"matjohnson.info","indices":[0,22]}]},"description":{"urls":[]}},"protected":false,"followers_count":62114,"friends_count":947,"listed_count":660,"created_at":"Sat Apr 12 16:55:27 +0000 2008","favourites_count":4920,"utc_offset":-21600,"time_zone":"Central Time (US & Canada)","geo_enabled":false,"verified":true,"statuses_count":22410,"lang":"en","contributors_enabled":false,"is_translator":false,"is_translation_enabled":false,"profile_background_color":"9AE8CF","profile_background_image_url":"http://pbs.twimg.com/profile_background_images/519129027169116160/Z3QVoq3r.png","profile_background_image_url_https":"https://pbs.twimg.com/profile_background_images/519129027169116160/Z3QVoq3r.png","profile_background_tile":true,"profile_image_url":"http://pbs.twimg.com/profile_images/1179503891/twit_pic_for_me_normal.jpg","profile_image_url_https":"https://pbs.twimg.com/profile_images/1179503891/twit_pic_for_me_normal.jpg","profile_banner_url":"https://pbs.twimg.com/profile_banners/14369768/1413826018","profile_link_color":"483EDE","profile_sidebar_border_color":"FFFFFF","profile_sidebar_fill_color":"D7EBF2","profile_text_color":"D72C1D","profile_use_background_image":true,"default_profile":false,"default_profile_image":false,"following":false,"follow_request_sent":false,"notifications":false},{"id":15603374,"id_str":"15603374","name":"Ian Padgham","screen_name":"origiful","location":"San Francisco, CA","profile_location":null,"description":"Video Producer & Artist.","url":"http://t.co/pO26ZvREzn","entities":{"url":{"urls":[{"url":"http://t.co/pO26ZvREzn","expanded_url":"http://origiful.com/vine","display_url":"origiful.com/vine","indices":[0,22]}]},"description":{"urls":[]}},"protected":false,"followers_count":32281,"friends_count":418,"listed_count":337,"created_at":"Fri Jul 25 20:36:15 +0000 2008","favourites_count":4240,"utc_offset":-28800,"time_zone":"Pacific Time (US & Canada)","geo_enabled":true,"verified":false,"statuses_count":3918,"lang":"en","contributors_enabled":false,"is_translator":false,"is_translation_enabled":false,"profile_background_color":"131516","profile_background_image_url":"http://pbs.twimg.com/profile_background_images/344918034408746141/28ac6a14bc1b96138cd0acae3ae357c2.jpeg","profile_background_image_url_https":"https://pbs.twimg.com/profile_background_images/344918034408746141/28ac6a14bc1b96138cd0acae3ae357c2.jpeg","profile_background_tile":true,"profile_image_url":"http://pbs.twimg.com/profile_images/3760492781/129672f7e46b9842d9833d38f006c45a_normal.jpeg","profile_image_url_https":"https://pbs.twimg.com/profile_images/3760492781/129672f7e46b9842d9833d38f006c45a_normal.jpeg","profile_banner_url":"https://pbs.twimg.com/profile_banners/15603374/1398203296","profile_link_color":"009999","profile_sidebar_border_color":"FFFFFF","profile_sidebar_fill_color":"EFEFEF","profile_text_color":"333333","profile_use_background_image":true,"default_profile":false,"default_profile_image":false,"following":false,"follow_request_sent":false,"notifications":false},{"id":15746556,"id_str":"15746556","name":"5-Second Films","screen_name":"5sf","location":"Los Angeles","profile_location":null,"description":"Shot a new film every weekday for over 5 years. Shooting the feature film, Dude Bro Party Massacre 3.\n#dbpm3","url":"http://t.co/kZF78LKvn8","entities":{"url":{"urls":[{"url":"http://t.co/kZF78LKvn8","expanded_url":"http://5secondfilms.com","display_url":"5secondfilms.com","indices":[0,22]}]},"description":{"urls":[]}},"protected":false,"followers_count":85597,"friends_count":689,"listed_count":531,"created_at":"Wed Aug 06 05:32:36 +0000 2008","favourites_count":534,"utc_offset":-28800,"time_zone":"Pacific Time (US & Canada)","geo_enabled":true,"verified":false,"statuses_count":8309,"lang":"en","contributors_enabled":false,"is_translator":false,"is_translation_enabled":false,"profile_background_color":"000000","profile_background_image_url":"http://pbs.twimg.com/profile_background_images/378800000012704304/1762f73f230ca4a7227c638e7faf7b8d.jpeg","profile_background_image_url_https":"https://pbs.twimg.com/profile_background_images/378800000012704304/1762f73f230ca4a7227c638e7faf7b8d.jpeg","profile_background_tile":true,"profile_image_url":"http://pbs.twimg.com/profile_images/378800000072105830/88de3ef2cc000bd65059b68df913522e_normal.jpeg","profile_image_url_https":"https://pbs.twimg.com/profile_images/378800000072105830/88de3ef2cc000bd65059b68df913522e_normal.jpeg","profile_banner_url":"https://pbs.twimg.com/profile_banners/15746556/1391935322","profile_link_color":"0084B4","profile_sidebar_border_color":"000000","profile_sidebar_fill_color":"DDFFCC","profile_text_color":"333333","profile_use_background_image":true,"default_profile":false,"default_profile_image":false,"following":false,"follow_request_sent":false,"notifications":false},{"id":20690398,"id_str":"20690398","name":"Duncan Jones","screen_name":"ManMadeMoon","location":"","profile_location":null,"description":"Director of Moon, Source Code & Warcraft.  So far...","url":"http://t.co/2FXrknUthQ","entities":{"url":{"urls":[{"url":"http://t.co/2FXrknUthQ","expanded_url":"http://blog.manmademovies.co.uk/","display_url":"blog.manmademovies.co.uk","indices":[0,22]}]},"description":{"urls":[]}},"protected":false,"followers_count":179543,"friends_count":424,"listed_count":3167,"created_at":"Thu Feb 12 16:28:43 +0000 2009","favourites_count":534,"utc_offset":0,"time_zone":"London","geo_enabled":false,"verified":true,"statuses_count":44690,"lang":"en","contributors_enabled":false,"is_translator":false,"is_translation_enabled":false,"profile_background_color":"000000","profile_background_image_url":"http://pbs.twimg.com/profile_background_images/10547770/manmademoon.jpg","profile_background_image_url_https":"https://pbs.twimg.com/profile_background_images/10547770/manmademoon.jpg","profile_background_tile":false,"profile_image_url":"http://pbs.twimg.com/profile_images/1344744333/duncan8bit_normal.jpg","profile_image_url_https":"https://pbs.twimg.com/profile_images/1344744333/duncan8bit_normal.jpg","profile_link_color":"039DFC","profile_sidebar_border_color":"595959","profile_sidebar_fill_color":"1C1C1C","profile_text_color":"A6A6A6","profile_use_background_image":true,"default_profile":false,"default_profile_image":false,"following":false,"follow_request_sent":false,"notifications":false},{"id":21882128,"id_str":"21882128","name":"Owen Pallett","screen_name":"owenpallett","location":"Montreal, Quebec","profile_location":null,"description":"Thoughts disguised as ringtones","url":"http://t.co/dZaEao5oqD","entities":{"url":{"urls":[{"url":"http://t.co/dZaEao5oqD","expanded_url":"http://www.owenpalletteternal.com","display_url":"owenpalletteternal.com","indices":[0,22]}]},"description":{"urls":[]}},"protected":false,"followers_count":90940,"friends_count":1060,"listed_count":1944,"created_at":"Wed Feb 25 16:19:35 +0000 2009","favourites_count":3194,"utc_offset":-21600,"time_zone":"Central Time (US & Canada)","geo_enabled":false,"verified":true,"statuses_count":7520,"lang":"en","contributors_enabled":false,"is_translator":false,"is_translation_enabled":false,"profile_background_color":"1A1B1F","profile_background_image_url":"http://pbs.twimg.com/profile_background_images/381830495/LFM_WONG.jpg","profile_background_image_url_https":"https://pbs.twimg.com/profile_background_images/381830495/LFM_WONG.jpg","profile_background_tile":true,"profile_image_url":"http://pbs.twimg.com/profile_images/526938898564268032/G7bstqy2_normal.jpeg","profile_image_url_https":"https://pbs.twimg.com/profile_images/526938898564268032/G7bstqy2_normal.jpeg","profile_link_color":"2FC2EF","profile_sidebar_border_color":"181A1E","profile_sidebar_fill_color":"252429","profile_text_color":"666666","profile_use_background_image":true,"default_profile":false,"default_profile_image":false,"following":false,"follow_request_sent":false,"notifications":false},{"id":22070897,"id_str":"22070897","name":"Doug Lussenhop","screen_name":"douggpound","location":"Low Sandwiches, California","profile_location":null,"description":"DJ Douggpound in the mix. http://t.co/5pFAxAmhk3","url":"http://t.co/C983nbSX6i","entities":{"url":{"urls":[{"url":"http://t.co/C983nbSX6i","expanded_url":"http://douggpound.com","display_url":"douggpound.com","indices":[0,22]}]},"description":{"urls":[{"url":"http://t.co/5pFAxAmhk3","expanded_url":"http://youtu.be/6Ts9ZB3N1vw","display_url":"youtu.be/6Ts9ZB3N1vw","indices":[26,48]}]}},"protected":false,"followers_count":76232,"friends_count":729,"listed_count":806,"created_at":"Thu Feb 26 22:16:27 +0000 2009","favourites_count":2842,"utc_offset":-28800,"time_zone":"Pacific Time (US & Canada)","geo_enabled":false,"verified":true,"statuses_count":6261,"lang":"en","contributors_enabled":false,"is_translator":false,"is_translation_enabled":false,"profile_background_color":"131516","profile_background_image_url":"http://pbs.twimg.com/profile_background_images/378800000046691778/b21e82761f89733ed79befe2ad8d484b.png","profile_background_image_url_https":"https://pbs.twimg.com/profile_background_images/378800000046691778/b21e82761f89733ed79befe2ad8d484b.png","profile_background_tile":true,"profile_image_url":"http://pbs.twimg.com/profile_images/510506061594247168/2Mcfm2kS_normal.png","profile_image_url_https":"https://pbs.twimg.com/profile_images/510506061594247168/2Mcfm2kS_normal.png","profile_banner_url":"https://pbs.twimg.com/profile_banners/22070897/1372795415","profile_link_color":"009999","profile_sidebar_border_color":"FFFFFF","profile_sidebar_fill_color":"EFEFEF","profile_text_color":"333333","profile_use_background_image":false,"default_profile":false,"default_profile_image":false,"following":false,"follow_request_sent":false,"notifications":false},{"id":24465880,"id_str":"24465880","name":"Troy Livesay","screen_name":"troylivesay","location":"Port Au Prince, Haiti","profile_location":null,"description":"Husband of Tara Livesay - Father of seven super kids - Living and loving in Port-au-Prince, Haiti working with http://t.co/IQcYWkz1kL.","url":"http://t.co/to2bVd3wNI","entities":{"url":{"urls":[{"url":"http://t.co/to2bVd3wNI","expanded_url":"http://www.livesayhaiti.blogspot.com","display_url":"livesayhaiti.blogspot.com","indices":[0,22]}]},"description":{"urls":[{"url":"http://t.co/IQcYWkz1kL","expanded_url":"http://www.heartlineministries.org","display_url":"heartlineministries.org","indices":[111,133]}]}},"protected":false,"followers_count":55482,"friends_count":853,"listed_count":506,"created_at":"Sun Mar 15 01:33:47 +0000 2009","favourites_count":4903,"utc_offset":-18000,"time_zone":"Eastern Time (US & Canada)","geo_enabled":false,"verified":false,"statuses_count":10927,"lang":"en","contributors_enabled":false,"is_translator":false,"is_translation_enabled":false,"profile_background_color":"022330","profile_background_image_url":"http://pbs.twimg.com/profile_background_images/690436338/12114b2865a669983b9e4426d13806ae.jpeg","profile_background_image_url_https":"https://pbs.twimg.com/profile_background_images/690436338/12114b2865a669983b9e4426d13806ae.jpeg","profile_background_tile":false,"profile_image_url":"http://pbs.twimg.com/profile_images/1106732248/troy_livesay_normal.jpg","profile_image_url_https":"https://pbs.twimg.com/profile_images/1106732248/troy_livesay_normal.jpg","profile_banner_url":"https://pbs.twimg.com/profile_banners/24465880/1350863102","profile_link_color":"0084B4","profile_sidebar_border_color":"FFFFFF","profile_sidebar_fill_color":"C0DFEC","profile_text_color":"333333","profile_use_background_image":true,"default_profile":false,"default_profile_image":false,"following":false,"follow_request_sent":false,"notifications":false},{"id":30343716,"id_str":"30343716","name":"San Francisco DEM","screen_name":"SF_emergency","location":"San Francisco","profile_location":null,"description":"The official profile for the San Francisco Department of Emergency Management for informational purposes only.","url":"http://t.co/mFhGVUWW1Q","entities":{"url":{"urls":[{"url":"http://t.co/mFhGVUWW1Q","expanded_url":"http://www.sfgov.org/dem","display_url":"sfgov.org/dem","indices":[0,22]}]},"description":{"urls":[]}},"protected":false,"followers_count":69795,"friends_count":130,"listed_count":1049,"created_at":"Fri Apr 10 23:43:04 +0000 2009","favourites_count":10,"utc_offset":-28800,"time_zone":"Pacific Time (US & Canada)","geo_enabled":true,"verified":true,"statuses_count":1616,"lang":"en","contributors_enabled":false,"is_translator":false,"is_translation_enabled":true,"profile_background_color":"A9CAE0","profile_background_image_url":"http://abs.twimg.com/images/themes/theme1/bg.png","profile_background_image_url_https":"https://abs.twimg.com/images/themes/theme1/bg.png","profile_background_tile":false,"profile_image_url":"http://pbs.twimg.com/profile_images/148983301/SFDEM2_normal.gif","profile_image_url_https":"https://pbs.twimg.com/profile_images/148983301/SFDEM2_normal.gif","profile_link_color":"B4382D","profile_sidebar_border_color":"BDDCAD","profile_sidebar_fill_color":"EDE9E8","profile_text_color":"333333","profile_use_background_image":false,"default_profile":false,"default_profile_image":false,"following":false,"follow_request_sent":false,"notifications":false},{"id":60180322,"id_str":"60180322","name":"Steve Mesler","screen_name":"SteveMesler","location":"","profile_location":null,"description":"President & CEO @ClassroomChamps TED-Ed Educator. I sit really fast and speak here & there. 3-time Olympian, 1-time Golden.","url":"http://t.co/t8V0bP60H3","entities":{"url":{"urls":[{"url":"http://t.co/t8V0bP60H3","expanded_url":"http://stevemesler.com","display_url":"stevemesler.com","indices":[0,22]}]},"description":{"urls":[]}},"protected":false,"followers_count":88907,"friends_count":1036,"listed_count":699,"created_at":"Sat Jul 25 23:47:59 +0000 2009","favourites_count":1485,"utc_offset":null,"time_zone":null,"geo_enabled":true,"verified":true,"statuses_count":7524,"lang":"en","contributors_enabled":false,"is_translator":false,"is_translation_enabled":false,"profile_background_color":"000000","profile_background_image_url":"http://pbs.twimg.com/profile_background_images/435286437504634880/8PtPHj4Q.jpeg","profile_background_image_url_https":"https://pbs.twimg.com/profile_background_images/435286437504634880/8PtPHj4Q.jpeg","profile_background_tile":false,"profile_image_url":"http://pbs.twimg.com/profile_images/469320143072264193/ZwXEJvni_normal.jpeg","profile_image_url_https":"https://pbs.twimg.com/profile_images/469320143072264193/ZwXEJvni_normal.jpeg","profile_banner_url":"https://pbs.twimg.com/profile_banners/60180322/1400820893","profile_link_color":"60AFDD","profile_sidebar_border_color":"FFFFFF","profile_sidebar_fill_color":"F3F3F3","profile_text_color":"000000","profile_use_background_image":true,"default_profile":false,"default_profile_image":false,"following":false,"follow_request_sent":false,"notifications":false},{"id":95952643,"id_str":"95952643","name":"Elantra Cuddles","screen_name":"TimeLostBatman","location":"","profile_location":null,"description":"SAME BAT TIME? IT'S NEVER THE SAME BAT TIME ANYMORE!","url":null,"entities":{"description":{"urls":[]}},"protected":false,"followers_count":87663,"friends_count":1,"listed_count":672,"created_at":"Thu Dec 10 18:10:41 +0000 2009","favourites_count":2,"utc_offset":-21600,"time_zone":"Central Time (US & Canada)","geo_enabled":false,"verified":false,"statuses_count":759,"lang":"en","contributors_enabled":false,"is_translator":false,"is_translation_enabled":false,"profile_background_color":"C0DEED","profile_background_image_url":"http://abs.twimg.com/images/themes/theme1/bg.png","profile_background_image_url_https":"https://abs.twimg.com/images/themes/theme1/bg.png","profile_background_tile":false,"profile_image_url":"http://pbs.twimg.com/profile_images/418312624674070529/yFmENb7G_normal.jpeg","profile_image_url_https":"https://pbs.twimg.com/profile_images/418312624674070529/yFmENb7G_normal.jpeg","profile_link_color":"0084B4","profile_sidebar_border_color":"C0DEED","profile_sidebar_fill_color":"DDEEF6","profile_text_color":"333333","profile_use_background_image":true,"default_profile":true,"default_profile_image":false,"following":false,"follow_request_sent":false,"notifications":false},{"id":342457761,"id_str":"342457761","name":"chase budinger","screen_name":"CBudinger","location":"Minneapolis","profile_location":null,"description":"play basketball for a living... what a life!","url":null,"entities":{"description":{"urls":[]}},"protected":false,"followers_count":56663,"friends_count":78,"listed_count":582,"created_at":"Tue Jul 26 01:40:46 +0000 2011","favourites_count":23,"utc_offset":null,"time_zone":null,"geo_enabled":true,"verified":true,"statuses_count":2033,"lang":"en","contributors_enabled":false,"is_translator":false,"is_translation_enabled":false,"profile_background_color":"C0DEED","profile_background_image_url":"http://abs.twimg.com/images/themes/theme1/bg.png","profile_background_image_url_https":"https://abs.twimg.com/images/themes/theme1/bg.png","profile_background_tile":false,"profile_image_url":"http://pbs.twimg.com/profile_images/421328621865672705/zxGmoTrB_normal.jpeg","profile_image_url_https":"https://pbs.twimg.com/profile_images/421328621865672705/zxGmoTrB_normal.jpeg","profile_link_color":"0084B4","profile_sidebar_border_color":"C0DEED","profile_sidebar_fill_color":"DDEEF6","profile_text_color":"333333","profile_use_background_image":true,"default_profile":true,"default_profile_image":false,"following":false,"follow_request_sent":false,"notifications":false},{"id":467507215,"id_str":"467507215","name":"Herdwick Shepherd","screen_name":"herdyshepherd1","location":"Lake District, England","profile_location":null,"description":"We farm Herdwick sheep in the Lake District. This twitter feed is to share updates on our shepherding year. Do other things sometimes as well, like writing.","url":null,"entities":{"description":{"urls":[]}},"protected":false,"followers_count":30823,"friends_count":1969,"listed_count":423,"created_at":"Wed Jan 18 15:02:27 +0000 2012","favourites_count":13322,"utc_offset":null,"time_zone":null,"geo_enabled":false,"verified":false,"statuses_count":12526,"lang":"en","contributors_enabled":false,"is_translator":false,"is_translation_enabled":false,"profile_background_color":"C0DEED","profile_background_image_url":"http://abs.twimg.com/images/themes/theme1/bg.png","profile_background_image_url_https":"https://abs.twimg.com/images/themes/theme1/bg.png","profile_background_tile":false,"profile_image_url":"http://pbs.twimg.com/profile_images/510524535935090688/K1nkVWYZ_normal.jpeg","profile_image_url_https":"https://pbs.twimg.com/profile_images/510524535935090688/K1nkVWYZ_normal.jpeg","profile_banner_url":"https://pbs.twimg.com/profile_banners/467507215/1413097112","profile_link_color":"0084B4","profile_sidebar_border_color":"C0DEED","profile_sidebar_fill_color":"DDEEF6","profile_text_color":"333333","profile_use_background_image":true,"default_profile":true,"default_profile_image":false,"following":false,"follow_request_sent":false,"notifications":false}],"size":51,"slug":"staff-picks","name":"Staff Picks"}