{"users":[{"id":16365636,"id_str":"16365636","name":"TripAdvisor","screen_name":"TripAdvisor","location":"","profile_location":null,"description":"Helping travelers plan and have the perfect trip.","url":"http://t.co/3OBDrbf1Kg","entities":{"url":{"urls":[{"url":"http://t.co/3OBDrbf1Kg","expanded_url":"http://tripadvisor.com","display_url":"tripadvisor.com","indices":[0,22]}]},"description":{"urls":[]}},"protected":false,"followers_count":1684903,"friends_count":2931,"listed_count":12594,"created_at":"Fri Sep 19 16:40:46 +0000 2008","favourites_count":1596,"utc_offset":-18000,"time_zone":"Eastern Time (US & Canada)","geo_enabled":true,"verified":true,"statuses_count":11141,"lang":"en","contributors_enabled":false,"is_translator":false,"is_translation_enabled":false,"profile_background_color":"9AE4E8","profile_background_image_url":"http://pbs.twimg.com/profile_background_images/437024728994168832/FucY3a_G.jpeg","profile_background_image_url_https":"https://pbs.twimg.com/profile_background_images/437024728994168832/FucY3a_G.jpeg","profile_background_tile":false,"profile_image_url":"http://pbs.twimg.com/profile_images/472494793616945153/nAKMJI27_normal.jpeg","profile_image_url_https":"https://pbs.twimg.com/profile_images/472494793616945153/nAKMJI27_normal.jpeg","profile_banner_url":"https://pbs.twimg.com/profile_banners/16365636/1402342721","profile_link_color":"0084B4","profile_sidebar_border_color":"FFFFFF","profile_sidebar_fill_color":"DDFFCC","profile_text_color":"333333","profile_use_background_image":true,"default_profile":false,"default_profile_image":false,"following":false,"follow_request_sent":false,"notifications":false},{"id":15066760,"id_str":"15066760","name":"Lonely Planet","screen_name":"lonelyplanet","location":"Everywhere, all the time","profile_location":null,"description":"Tweeting (& RT'ing) the best in travel. 1/Follow us 2/Tag your tweets with #lp 3/We read your posts 4/We re-tweet the best of them.","url":"http://t.co/srKyq4HbMN","entities":{"url":{"urls":[{"url":"http://t.co/srKyq4HbMN","expanded_url":"http://www.lonelyplanet.com","display_url":"lonelyplanet.com","indices":[0,22]}]},"description":{"urls":[]}},"protected":false,"followers_count":1868309,"friends_count":790505,"listed_count":22679,"created_at":"Mon Jun 09 22:53:07 +0000 2008","favourites_count":13885,"utc_offset":-28800,"time_zone":"Pacific Time (US & Canada)","geo_enabled":true,"verified":true,"statuses_count":31637,"lang":"en","contributors_enabled":false,"is_translator":false,"is_translation_enabled":false,"profile_background_color":"061128","profile_background_image_url":"http://pbs.twimg.com/profile_background_images/529644512679694336/oQYGfC9m.jpeg","profile_background_image_url_https":"https://pbs.twimg.com/profile_background_images/529644512679694336/oQYGfC9m.jpeg","profile_background_tile":true,"profile_image_url":"http://pbs.twimg.com/profile_images/3623975823/701a6ec1ac1c53f98c386889214d6310_normal.png","profile_image_url_https":"https://pbs.twimg.com/profile_images/3623975823/701a6ec1ac1c53f98c386889214d6310_normal.png","profile_banner_url":"https://pbs.twimg.com/profile_banners/15066760/1415111769","profile_link_color":"0077CC","profile_sidebar_border_color":"FFFFFF","profile_sidebar_fill_color":"DFE7F2","profile_text_color":"11111A","profile_use_background_image":true,"default_profile":false,"default_profile_image":false,"following":false,"follow_request_sent":false,"notifications":false},{"id":19195914,"id_str":"19195914","name":"Zagat","screen_name":"Zagat","location":"Global","profile_location":null,"description":"News, events and reviews for restaurants, shopping, nightlife and travel.","url":"http://t.co/uy0WqmJpN8","entities":{"url":{"urls":[{"url":"http://t.co/uy0WqmJpN8","expanded_url":"http://www.zagat.com","display_url":"zagat.com","indices":[0,22]}]},"description":{"urls":[]}},"protected":false,"followers_count":956508,"friends_count":125363,"listed_count":10318,"created_at":"Mon Jan 19 18:55:06 +0000 2009","favourites_count":643,"utc_offset":-18000,"time_zone":"Eastern Time (US & Canada)","geo_enabled":false,"verified":true,"statuses_count":29652,"lang":"en","contributors_enabled":false,"is_translator":false,"is_translation_enabled":false,"profile_background_color":"890019","profile_background_image_url":"http://pbs.twimg.com/profile_background_images/378800000181462974/azduo3JT.png","profile_background_image_url_https":"https://pbs.twimg.com/profile_background_images/378800000181462974/azduo3JT.png","profile_background_tile":false,"profile_image_url":"http://pbs.twimg.com/profile_images/458692618117853185/jxnXwt26_normal.png","profile_image_url_https":"https://pbs.twimg.com/profile_images/458692618117853185/jxnXwt26_normal.png","profile_banner_url":"https://pbs.twimg.com/profile_banners/19195914/1398194626","profile_link_color":"890019","profile_sidebar_border_color":"FFFFFF","profile_sidebar_fill_color":"F6DED5","profile_text_color":"333333","profile_use_background_image":true,"default_profile":false,"default_profile_image":false,"following":false,"follow_request_sent":false,"notifications":false},{"id":19110632,"id_str":"19110632","name":"The Travel Magazine","screen_name":"TravelMagazine","location":"London and the French Riviera","profile_location":null,"description":"Get the latest travel news, articles, reports, guides, special offers, competitions and more from http://t.co/T7bnCm7vZZ - we'd love to hear from you too.","url":"http://t.co/VU79FGRoTD","entities":{"url":{"urls":[{"url":"http://t.co/VU79FGRoTD","expanded_url":"http://www.thetravelmagazine.net","display_url":"thetravelmagazine.net","indices":[0,22]}]},"description":{"urls":[{"url":"http://t.co/T7bnCm7vZZ","expanded_url":"http://TheTravelMagazine.net","display_url":"TheTravelMagazine.net","indices":[98,120]}]}},"protected":false,"followers_count":1055716,"friends_count":472,"listed_count":8638,"created_at":"Sat Jan 17 13:59:56 +0000 2009","favourites_count":342,"utc_offset":0,"time_zone":"London","geo_enabled":true,"verified":false,"statuses_count":8178,"lang":"en","contributors_enabled":false,"is_translator":false,"is_translation_enabled":false,"profile_background_color":"9AE4E8","profile_background_image_url":"http://pbs.twimg.com/profile_background_images/566606278/pgm83h8xjpm2nhtjprs1.jpeg","profile_background_image_url_https":"https://pbs.twimg.com/profile_background_images/566606278/pgm83h8xjpm2nhtjprs1.jpeg","profile_background_tile":true,"profile_image_url":"http://pbs.twimg.com/profile_images/1828695254/ttm_square_normal.jpg","profile_image_url_https":"https://pbs.twimg.com/profile_images/1828695254/ttm_square_normal.jpg","profile_banner_url":"https://pbs.twimg.com/profile_banners/19110632/1413178858","profile_link_color":"0084B4","profile_sidebar_border_color":"FFFFFF","profile_sidebar_fill_color":"DDFFCC","profile_text_color":"333333","profile_use_background_image":true,"default_profile":false,"default_profile_image":false,"following":false,"follow_request_sent":false,"notifications":false},{"id":16211434,"id_str":"16211434","name":"Travel + Leisure","screen_name":"TravlandLeisure","location":"New York, NY","profile_location":null,"description":"Your connection to the world of travel, brought to you by our editors. Questions? Stories? Please share! Social media terms: http://t.co/s14tZDmFoi","url":"http://t.co/vmvNyo6nXZ","entities":{"url":{"urls":[{"url":"http://t.co/vmvNyo6nXZ","expanded_url":"http://www.travelandleisure.com","display_url":"travelandleisure.com","indices":[0,22]}]},"description":{"urls":[{"url":"http://t.co/s14tZDmFoi","expanded_url":"http://tandl.me/mediaterms","display_url":"tandl.me/mediaterms","indices":[125,147]}]}},"protected":false,"followers_count":947712,"friends_count":832,"listed_count":10405,"created_at":"Tue Sep 09 21:16:34 +0000 2008","favourites_count":5597,"utc_offset":-18000,"time_zone":"Eastern Time (US & Canada)","geo_enabled":true,"verified":true,"statuses_count":24605,"lang":"en","contributors_enabled":false,"is_translator":false,"is_translation_enabled":false,"profile_background_color":"131516","profile_background_image_url":"http://pbs.twimg.com/profile_background_images/524220801629704192/SdR6lzY8.jpeg","profile_background_image_url_https":"https://pbs.twimg.com/profile_background_images/524220801629704192/SdR6lzY8.jpeg","profile_background_tile":true,"profile_image_url":"http://pbs.twimg.com/profile_images/3704055283/7830ca91dc1c7e34a27100568e628a93_normal.png","profile_image_url_https":"https://pbs.twimg.com/profile_images/3704055283/7830ca91dc1c7e34a27100568e628a93_normal.png","profile_banner_url":"https://pbs.twimg.com/profile_banners/16211434/1413818867","profile_link_color":"FA0824","profile_sidebar_border_color":"000000","profile_sidebar_fill_color":"EFEFEF","profile_text_color":"333333","profile_use_background_image":true,"default_profile":false,"default_profile_image":false,"following":false,"follow_request_sent":false,"notifications":false},{"id":36184220,"id_str":"36184220","name":"NatGeoTravel","screen_name":"NatGeoTravel","location":"Washington, D.C. ","profile_location":null,"description":"Approach travel from every angle: National Geographic Traveler magazine, guides, trips, daily photos & tips. Official account for National Geographic Travel","url":"http://t.co/dupuBQ9mie","entities":{"url":{"urls":[{"url":"http://t.co/dupuBQ9mie","expanded_url":"http://travel.nationalgeographic.com/","display_url":"travel.nationalgeographic.com","indices":[0,22]}]},"description":{"urls":[]}},"protected":false,"followers_count":1114805,"friends_count":180,"listed_count":11313,"created_at":"Tue Apr 28 21:10:42 +0000 2009","favourites_count":3523,"utc_offset":-18000,"time_zone":"Quito","geo_enabled":false,"verified":false,"statuses_count":15197,"lang":"en","contributors_enabled":false,"is_translator":false,"is_translation_enabled":false,"profile_background_color":"0A0A0A","profile_background_image_url":"http://pbs.twimg.com/profile_background_images/517755512482308098/U25kFwUR.jpeg","profile_background_image_url_https":"https://pbs.twimg.com/profile_background_images/517755512482308098/U25kFwUR.jpeg","profile_background_tile":false,"profile_image_url":"http://pbs.twimg.com/profile_images/517674723728052224/5Mg1uPhW_normal.jpeg","profile_image_url_https":"https://pbs.twimg.com/profile_images/517674723728052224/5Mg1uPhW_normal.jpeg","profile_banner_url":"https://pbs.twimg.com/profile_banners/36184220/1412258288","profile_link_color":"0D9BBF","profile_sidebar_border_color":"FFFFFF","profile_sidebar_fill_color":"DFE6E4","profile_text_color":"4D454D","profile_use_background_image":true,"default_profile":false,"default_profile_image":false,"following":false,"follow_request_sent":false,"notifications":false},{"id":11856482,"id_str":"11856482","name":"NBC News Travel","screen_name":"NBCNewsTravel","location":"","profile_location":null,"description":"Getting there is half the fun, so the saying goes. Read about top travel news, issues of the day and the joy and hassle of traveling.","url":"http://t.co/auGnZqZr2b","entities":{"url":{"urls":[{"url":"http://t.co/auGnZqZr2b","expanded_url":"http://nbcnews.com/business/travel","display_url":"nbcnews.com/business/travel","indices":[0,22]}]},"description":{"urls":[]}},"protected":false,"followers_count":434200,"friends_count":1282,"listed_count":4500,"created_at":"Fri Jan 04 22:19:38 +0000 2008","favourites_count":96,"utc_offset":-18000,"time_zone":"Eastern Time (US & Canada)","geo_enabled":false,"verified":true,"statuses_count":14792,"lang":"en","contributors_enabled":false,"is_translator":false,"is_translation_enabled":false,"profile_background_color":"062131","profile_background_image_url":"http://pbs.twimg.com/profile_background_images/378800000181862422/yVienzNu.jpeg","profile_background_image_url_https":"https://pbs.twimg.com/profile_background_images/378800000181862422/yVienzNu.jpeg","profile_background_tile":true,"profile_image_url":"http://pbs.twimg.com/profile_images/431114571760152576/d-1WlpAR_normal.png","profile_image_url_https":"https://pbs.twimg.com/profile_images/431114571760152576/d-1WlpAR_normal.png","profile_banner_url":"https://pbs.twimg.com/profile_banners/11856482/1398197832","profile_link_color":"5172A0","profile_sidebar_border_color":"FFFFFF","profile_sidebar_fill_color":"EEEEEE","profile_text_color":"000000","profile_use_background_image":true,"default_profile":false,"default_profile_image":false,"following":false,"follow_request_sent":false,"notifications":false},{"id":14363353,"id_str":"14363353","name":"Travel Channel","screen_name":"travelchannel","location":"All over the place","profile_location":null,"description":"The official Twitter account of Travel Channel (US). Follow us to talk about all things travel!","url":"http://t.co/v5zIooJJbW","entities":{"url":{"urls":[{"url":"http://t.co/v5zIooJJbW","expanded_url":"http://www.travelchannel.com","display_url":"travelchannel.com","indices":[0,22]}]},"description":{"urls":[]}},"protected":false,"followers_count":997165,"friends_count":2675,"listed_count":10193,"created_at":"Fri Apr 11 18:31:13 +0000 2008","favourites_count":370,"utc_offset":-18000,"time_zone":"Eastern Time (US & Canada)","geo_enabled":false,"verified":true,"statuses_count":13915,"lang":"en","contributors_enabled":false,"is_translator":false,"is_translation_enabled":false,"profile_background_color":"000000","profile_background_image_url":"http://pbs.twimg.com/profile_background_images/378800000161216971/JJ6VZ-EM.jpeg","profile_background_image_url_https":"https://pbs.twimg.com/profile_background_images/378800000161216971/JJ6VZ-EM.jpeg","profile_background_tile":false,"profile_image_url":"http://pbs.twimg.com/profile_images/524280281788735488/47wwxBT1_normal.jpeg","profile_image_url_https":"https://pbs.twimg.com/profile_images/524280281788735488/47wwxBT1_normal.jpeg","profile_banner_url":"https://pbs.twimg.com/profile_banners/14363353/1413833125","profile_link_color":"ED0439","profile_sidebar_border_color":"000000","profile_sidebar_fill_color":"DDFFCC","profile_text_color":"333333","profile_use_background_image":true,"default_profile":false,"default_profile_image":false,"following":false,"follow_request_sent":false,"notifications":false},{"id":28535982,"id_str":"28535982","name":"KAYAK","screen_name":"KAYAK","location":"Stamford, CT","profile_location":null,"description":"Compare hundreds of travel sites at once. Search One And Done.","url":"http://t.co/YIsefUtFZ2","entities":{"url":{"urls":[{"url":"http://t.co/YIsefUtFZ2","expanded_url":"http://www.KAYAK.com","display_url":"KAYAK.com","indices":[0,22]}]},"description":{"urls":[]}},"protected":false,"followers_count":529958,"friends_count":1296,"listed_count":5804,"created_at":"Fri Apr 03 10:10:05 +0000 2009","favourites_count":302,"utc_offset":-18000,"time_zone":"Eastern Time (US & Canada)","geo_enabled":false,"verified":true,"statuses_count":7602,"lang":"en","contributors_enabled":false,"is_translator":false,"is_translation_enabled":false,"profile_background_color":"F3F3F3","profile_background_image_url":"http://pbs.twimg.com/profile_background_images/663706333/c8umgafvb572f85g4pm5.jpeg","profile_background_image_url_https":"https://pbs.twimg.com/profile_background_images/663706333/c8umgafvb572f85g4pm5.jpeg","profile_background_tile":false,"profile_image_url":"http://pbs.twimg.com/profile_images/477490461125259264/ZVoXplKl_normal.png","profile_image_url_https":"https://pbs.twimg.com/profile_images/477490461125259264/ZVoXplKl_normal.png","profile_banner_url":"https://pbs.twimg.com/profile_banners/28535982/1404183031","profile_link_color":"0024B3","profile_sidebar_border_color":"000000","profile_sidebar_fill_color":"F3F3F3","profile_text_color":"212121","profile_use_background_image":true,"default_profile":false,"default_profile_image":false,"following":false,"follow_request_sent":false,"notifications":false},{"id":56377143,"id_str":"56377143","name":"Royal Dutch Airlines","screen_name":"KLM","location":"Amsterdam, the Netherlands","profile_location":null,"description":"Official global account of KLM. We are here 24/7 for service in 11 languages! Share personal details only in private messages!","url":"http://t.co/2mYq8RKb8Z","entities":{"url":{"urls":[{"url":"http://t.co/2mYq8RKb8Z","expanded_url":"http://www.klm.com","display_url":"klm.com","indices":[0,22]}]},"description":{"urls":[]}},"protected":false,"followers_count":1429871,"friends_count":43349,"listed_count":5553,"created_at":"Mon Jul 13 13:52:38 +0000 2009","favourites_count":128,"utc_offset":3600,"time_zone":"Amsterdam","geo_enabled":false,"verified":true,"statuses_count":441470,"lang":"en","contributors_enabled":false,"is_translator":false,"is_translation_enabled":false,"profile_background_color":"C0DEED","profile_background_image_url":"http://pbs.twimg.com/profile_background_images/378800000181388536/HZxC02AZ.jpeg","profile_background_image_url_https":"https://pbs.twimg.com/profile_background_images/378800000181388536/HZxC02AZ.jpeg","profile_background_tile":false,"profile_image_url":"http://pbs.twimg.com/profile_images/455425878395068416/Ld-G0Des_normal.png","profile_image_url_https":"https://pbs.twimg.com/profile_images/455425878395068416/Ld-G0Des_normal.png","profile_banner_url":"https://pbs.twimg.com/profile_banners/56377143/1415337610","profile_link_color":"00A3DE","profile_sidebar_border_color":"FFFFFF","profile_sidebar_fill_color":"C2DEEA","profile_text_color":"003145","profile_use_background_image":true,"default_profile":false,"default_profile_image":false,"following":false,"follow_request_sent":false,"notifications":false},{"id":5920532,"id_str":"5920532","name":"Delta","screen_name":"Delta","location":"Global","profile_location":null,"description":"Please visit http://t.co/0HM6SIFw4X                                                                                   \r\nif you require a formal response.","url":"http://t.co/XnVWrcmbym","entities":{"url":{"urls":[{"url":"http://t.co/XnVWrcmbym","expanded_url":"http://www.delta.com","display_url":"delta.com","indices":[0,22]}]},"description":{"urls":[{"url":"http://t.co/0HM6SIFw4X","expanded_url":"http://www.delta.com/talktous","display_url":"delta.com/talktous","indices":[13,35]}]}},"protected":false,"followers_count":813677,"friends_count":1086,"listed_count":8336,"created_at":"Thu May 10 04:31:14 +0000 2007","favourites_count":64,"utc_offset":-18000,"time_zone":"Eastern Time (US & Canada)","geo_enabled":true,"verified":true,"statuses_count":10543,"lang":"en","contributors_enabled":false,"is_translator":false,"is_translation_enabled":false,"profile_background_color":"003366","profile_background_image_url":"http://pbs.twimg.com/profile_background_images/148411800/delta_nose2.jpg","profile_background_image_url_https":"https://pbs.twimg.com/profile_background_images/148411800/delta_nose2.jpg","profile_background_tile":false,"profile_image_url":"http://pbs.twimg.com/profile_images/860130770/Supergraphic_normal.jpg","profile_image_url_https":"https://pbs.twimg.com/profile_images/860130770/Supergraphic_normal.jpg","profile_banner_url":"https://pbs.twimg.com/profile_banners/5920532/1348086512","profile_link_color":"C01932","profile_sidebar_border_color":"002950","profile_sidebar_fill_color":"F0F0F0","profile_text_color":"003366","profile_use_background_image":true,"default_profile":false,"default_profile_image":false,"following":false,"follow_request_sent":false,"notifications":false},{"id":1774391,"id_str":"1774391","name":"NY Times Travel","screen_name":"nytimestravel","location":"New York, NY","profile_location":null,"description":"Travel news and features from around the world.","url":"http://t.co/2XOSts2UYT","entities":{"url":{"urls":[{"url":"http://t.co/2XOSts2UYT","expanded_url":"http://www.nytimes.com/travel","display_url":"nytimes.com/travel","indices":[0,22]}]},"description":{"urls":[]}},"protected":false,"followers_count":592697,"friends_count":112,"listed_count":9842,"created_at":"Wed Mar 21 17:41:27 +0000 2007","favourites_count":42,"utc_offset":-18000,"time_zone":"Eastern Time (US & Canada)","geo_enabled":false,"verified":false,"statuses_count":9568,"lang":"en","contributors_enabled":false,"is_translator":false,"is_translation_enabled":false,"profile_background_color":"FFFFFF","profile_background_image_url":"http://pbs.twimg.com/profile_background_images/4403744/twitter_post.png","profile_background_image_url_https":"https://pbs.twimg.com/profile_background_images/4403744/twitter_post.png","profile_background_tile":true,"profile_image_url":"http://pbs.twimg.com/profile_images/2051674485/NYT_Twitter_travel_normal.png","profile_image_url_https":"https://pbs.twimg.com/profile_images/2051674485/NYT_Twitter_travel_normal.png","profile_link_color":"004276","profile_sidebar_border_color":"333333","profile_sidebar_fill_color":"E7EFF8","profile_text_color":"000000","profile_use_background_image":true,"default_profile":false,"default_profile_image":false,"following":false,"follow_request_sent":false,"notifications":false},{"id":24016767,"id_str":"24016767","name":"USA TODAY Travel","screen_name":"usatodaytravel","location":"USA TODAY HQ, McLean, Va.","profile_location":null,"description":"Get the latest travel news, deals and trends about flights, hotels, cruises and destinations from the USA TODAY Travel team.","url":"http://t.co/p0YhOajkZM","entities":{"url":{"urls":[{"url":"http://t.co/p0YhOajkZM","expanded_url":"http://travel.usatoday.com","display_url":"travel.usatoday.com","indices":[0,22]}]},"description":{"urls":[]}},"protected":false,"followers_count":423349,"friends_count":1967,"listed_count":4764,"created_at":"Thu Mar 12 19:41:28 +0000 2009","favourites_count":354,"utc_offset":-18000,"time_zone":"Eastern Time (US & Canada)","geo_enabled":false,"verified":true,"statuses_count":8765,"lang":"en","contributors_enabled":false,"is_translator":false,"is_translation_enabled":false,"profile_background_color":"C0DEED","profile_background_image_url":"http://pbs.twimg.com/profile_background_images/378800000092303658/d8aa5949bf34d8f8431799c7b10bee67.jpeg","profile_background_image_url_https":"https://pbs.twimg.com/profile_background_images/378800000092303658/d8aa5949bf34d8f8431799c7b10bee67.jpeg","profile_background_tile":false,"profile_image_url":"http://pbs.twimg.com/profile_images/463776448965128194/GAmVBcoq_normal.png","profile_image_url_https":"https://pbs.twimg.com/profile_images/463776448965128194/GAmVBcoq_normal.png","profile_banner_url":"https://pbs.twimg.com/profile_banners/24016767/1415030619","profile_link_color":"0000FF","profile_sidebar_border_color":"FFFFFF","profile_sidebar_fill_color":"B8E9F0","profile_text_color":"000000","profile_use_background_image":true,"default_profile":false,"default_profile_image":false,"following":false,"follow_request_sent":false,"notifications":false},{"id":12101862,"id_str":"12101862","name":"Virgin America","screen_name":"VirginAmerica","location":"23 US and Mexico destinations","profile_location":null,"description":"Welcome to the only mood-lit Twitter feed. Check out our blog http://t.co/rYssSyFrNc. For official complaints please visit us at http://t.co/cftZiNWDrG. Cheers!","url":"http://t.co/QHTh3hVPP9","entities":{"url":{"urls":[{"url":"http://t.co/QHTh3hVPP9","expanded_url":"http://vgn.am/VirginAmerica","display_url":"vgn.am/VirginAmerica","indices":[0,22]}]},"description":{"urls":[{"url":"http://t.co/rYssSyFrNc","expanded_url":"http://vgn.am/FlyerFeed","display_url":"vgn.am/FlyerFeed","indices":[62,84]},{"url":"http://t.co/cftZiNWDrG","expanded_url":"http://vgn.am/GstHlp","display_url":"vgn.am/GstHlp","indices":[129,151]}]}},"protected":false,"followers_count":598741,"friends_count":68733,"listed_count":8360,"created_at":"Fri Jan 11 05:17:36 +0000 2008","favourites_count":598,"utc_offset":-28800,"time_zone":"Pacific Time (US & Canada)","geo_enabled":true,"verified":true,"statuses_count":71016,"lang":"en","contributors_enabled":false,"is_translator":false,"is_translation_enabled":false,"profile_background_color":"000000","profile_background_image_url":"http://pbs.twimg.com/profile_background_images/171159725/cabin.jpg","profile_background_image_url_https":"https://pbs.twimg.com/profile_background_images/171159725/cabin.jpg","profile_background_tile":false,"profile_image_url":"http://pbs.twimg.com/profile_images/527865352244297728/2jCHDz6W_normal.png","profile_image_url_https":"https://pbs.twimg.com/profile_images/527865352244297728/2jCHDz6W_normal.png","profile_banner_url":"https://pbs.twimg.com/profile_banners/12101862/1413393037","profile_link_color":"7302CF","profile_sidebar_border_color":"FFFFFF","profile_sidebar_fill_color":"FFFFFF","profile_text_color":"222222","profile_use_background_image":true,"default_profile":false,"default_profile_image":false,"following":false,"follow_request_sent":false,"notifications":false},{"id":7212562,"id_str":"7212562","name":"Southwest Airlines","screen_name":"SouthwestAir","location":"Dallas, Texas","profile_location":null,"description":"The LUV Airline! For official concerns please use the link provided.","url":"http://t.co/Xr1vyZ0NsU","entities":{"url":{"urls":[{"url":"http://t.co/Xr1vyZ0NsU","expanded_url":"http://tinyurl.com/SWAContact","display_url":"tinyurl.com/SWAContact","indices":[0,22]}]},"description":{"urls":[]}},"protected":false,"followers_count":1750804,"friends_count":14374,"listed_count":13659,"created_at":"Mon Jul 02 19:56:44 +0000 2007","favourites_count":2327,"utc_offset":-21600,"time_zone":"Central Time (US & Canada)","geo_enabled":true,"verified":true,"statuses_count":35433,"lang":"en","contributors_enabled":false,"is_translator":false,"is_translation_enabled":false,"profile_background_color":"FFFFFF","profile_background_image_url":"http://pbs.twimg.com/profile_background_images/279117595/Twitter_background_7_2011.jpg","profile_background_image_url_https":"https://pbs.twimg.com/profile_background_images/279117595/Twitter_background_7_2011.jpg","profile_background_tile":false,"profile_image_url":"http://pbs.twimg.com/profile_images/508986645324918784/vbv1E0B0_normal.jpeg","profile_image_url_https":"https://pbs.twimg.com/profile_images/508986645324918784/vbv1E0B0_normal.jpeg","profile_banner_url":"https://pbs.twimg.com/profile_banners/7212562/1410186882","profile_link_color":"F47820","profile_sidebar_border_color":"FFFFFF","profile_sidebar_fill_color":"E3E3E3","profile_text_color":"000000","profile_use_background_image":true,"default_profile":false,"default_profile_image":false,"following":false,"follow_request_sent":false,"notifications":false},{"id":260907612,"id_str":"260907612","name":"United","screen_name":"united","location":"","profile_location":null,"description":"Welcome to our official Twitter page, where our conversations with you are 140 characters-friendly. We like hearing from you. Tweet us anytime.","url":"http://t.co/C3OPYCDhGt","entities":{"url":{"urls":[{"url":"http://t.co/C3OPYCDhGt","expanded_url":"http://unitedhub.com","display_url":"unitedhub.com","indices":[0,22]}]},"description":{"urls":[]}},"protected":false,"followers_count":548381,"friends_count":30152,"listed_count":4198,"created_at":"Fri Mar 04 21:23:11 +0000 2011","favourites_count":462,"utc_offset":-21600,"time_zone":"Central Time (US & Canada)","geo_enabled":false,"verified":true,"statuses_count":333353,"lang":"en","contributors_enabled":false,"is_translator":false,"is_translation_enabled":false,"profile_background_color":"000000","profile_background_image_url":"http://pbs.twimg.com/profile_background_images/454004296250454016/RQtA5shm.png","profile_background_image_url_https":"https://pbs.twimg.com/profile_background_images/454004296250454016/RQtA5shm.png","profile_background_tile":false,"profile_image_url":"http://pbs.twimg.com/profile_images/2449279853/Twitter-profile-mobile_0005_6_normal.jpg","profile_image_url_https":"https://pbs.twimg.com/profile_images/2449279853/Twitter-profile-mobile_0005_6_normal.jpg","profile_banner_url":"https://pbs.twimg.com/profile_banners/260907612/1411648983","profile_link_color":"0084B4","profile_sidebar_border_color":"FFFFFF","profile_sidebar_fill_color":"DDEEF6","profile_text_color":"333333","profile_use_background_image":true,"default_profile":false,"default_profile_image":false,"following":false,"follow_request_sent":false,"notifications":false},{"id":78084813,"id_str":"78084813","name":"US Airways","screen_name":"USAirways","location":"Tempe, Arizona, USA","profile_location":null,"description":"We are doing our best to listen & keep you updated. If you require an individual response please submit your complaint/compliment to http://t.co/aARRz5DT","url":"http://t.co/CrXeHiojGf","entities":{"url":{"urls":[{"url":"http://t.co/CrXeHiojGf","expanded_url":"http://www.usairways.com/Forms/CustomerRelations.aspx","display_url":"usairways.com/Forms/Customer…","indices":[0,22]}]},"description":{"urls":[{"url":"http://t.co/aARRz5DT","expanded_url":"http://bit.ly/epdY51","display_url":"bit.ly/epdY51","indices":[133,153]}]}},"protected":false,"followers_count":529209,"friends_count":29899,"listed_count":4847,"created_at":"Mon Sep 28 18:32:08 +0000 2009","favourites_count":43,"utc_offset":-28800,"time_zone":"Pacific Time (US & Canada)","geo_enabled":false,"verified":true,"statuses_count":153546,"lang":"en","contributors_enabled":false,"is_translator":false,"is_translation_enabled":false,"profile_background_color":"C0DEED","profile_background_image_url":"http://pbs.twimg.com/profile_background_images/632382312/cyfcyazuyyg0bp69qntp.jpeg","profile_background_image_url_https":"https://pbs.twimg.com/profile_background_images/632382312/cyfcyazuyyg0bp69qntp.jpeg","profile_background_tile":false,"profile_image_url":"http://pbs.twimg.com/profile_images/378800000678558531/af7becc4439d98abf5a7fb791b293b6f_normal.jpeg","profile_image_url_https":"https://pbs.twimg.com/profile_images/378800000678558531/af7becc4439d98abf5a7fb791b293b6f_normal.jpeg","profile_banner_url":"https://pbs.twimg.com/profile_banners/78084813/1383319041","profile_link_color":"0084B4","profile_sidebar_border_color":"FFFFFF","profile_sidebar_fill_color":"DDEEF6","profile_text_color":"333333","profile_use_background_image":true,"default_profile":false,"default_profile_image":false,"following":false,"follow_request_sent":false,"notifications":false},{"id":14825399,"id_str":"14825399","name":"Travelzoo","screen_name":"Travelzoo","location":"New York, NY","profile_location":null,"description":"Tweeting the best travel, entertainment and Local Deals selected by Deal Experts worldwide. Need help? http://t.co/5Kp4iDOF","url":"http://t.co/oyzgvfWuQ0","entities":{"url":{"urls":[{"url":"http://t.co/oyzgvfWuQ0","expanded_url":"http://www.travelzoo.com","display_url":"travelzoo.com","indices":[0,22]}]},"description":{"urls":[{"url":"http://t.co/5Kp4iDOF","expanded_url":"http://ow.ly/e2RKq","display_url":"ow.ly/e2RKq","indices":[103,123]}]}},"protected":false,"followers_count":444349,"friends_count":26348,"listed_count":5035,"created_at":"Sun May 18 22:37:28 +0000 2008","favourites_count":173,"utc_offset":-28800,"time_zone":"Pacific Time (US & Canada)","geo_enabled":false,"verified":true,"statuses_count":14921,"lang":"en","contributors_enabled":false,"is_translator":false,"is_translation_enabled":false,"profile_background_color":"000000","profile_background_image_url":"http://pbs.twimg.com/profile_background_images/670942415/dd876a2ec7bdb03624999674199b4950.jpeg","profile_background_image_url_https":"https://pbs.twimg.com/profile_background_images/670942415/dd876a2ec7bdb03624999674199b4950.jpeg","profile_background_tile":false,"profile_image_url":"http://pbs.twimg.com/profile_images/2648683780/0a09f5a92f132bba1d21bf5dea6f26d7_normal.png","profile_image_url_https":"https://pbs.twimg.com/profile_images/2648683780/0a09f5a92f132bba1d21bf5dea6f26d7_normal.png","profile_banner_url":"https://pbs.twimg.com/profile_banners/14825399/1414515950","profile_link_color":"CF0000","profile_sidebar_border_color":"000000","profile_sidebar_fill_color":"FFFFFF","profile_text_color":"000000","profile_use_background_image":true,"default_profile":false,"default_profile_image":false,"following":false,"follow_request_sent":false,"notifications":false},{"id":21662482,"id_str":"21662482","name":"AAATravel","screen_name":"AAA_Travel","location":"Heathrow, Fla.","profile_location":null,"description":"Official site of one of the largest US leisure travel agencies. Celebrating 78 Years of professional property inspections. DISCLAIMER: http://t.co/cweW7J5cRu","url":"http://t.co/DcPuEFOOWK","entities":{"url":{"urls":[{"url":"http://t.co/DcPuEFOOWK","expanded_url":"http://www.NewsRoom.AAA.com","display_url":"NewsRoom.AAA.com","indices":[0,22]}]},"description":{"urls":[{"url":"http://t.co/cweW7J5cRu","expanded_url":"http://bit.ly/1aqBwUX","display_url":"bit.ly/1aqBwUX","indices":[135,157]}]}},"protected":false,"followers_count":361287,"friends_count":1429,"listed_count":2777,"created_at":"Mon Feb 23 15:53:40 +0000 2009","favourites_count":8,"utc_offset":-18000,"time_zone":"Eastern Time (US & Canada)","geo_enabled":false,"verified":false,"statuses_count":5685,"lang":"en","contributors_enabled":false,"is_translator":false,"is_translation_enabled":false,"profile_background_color":"003366","profile_background_image_url":"http://pbs.twimg.com/profile_background_images/8622936/Twitter_background_lo-res.jpg","profile_background_image_url_https":"https://pbs.twimg.com/profile_background_images/8622936/Twitter_background_lo-res.jpg","profile_background_tile":false,"profile_image_url":"http://pbs.twimg.com/profile_images/474557999424368640/Sb2Tpn6T_normal.png","profile_image_url_https":"https://pbs.twimg.com/profile_images/474557999424368640/Sb2Tpn6T_normal.png","profile_banner_url":"https://pbs.twimg.com/profile_banners/21662482/1412603719","profile_link_color":"0084B4","profile_sidebar_border_color":"FFFFFF","profile_sidebar_fill_color":"DDFFCC","profile_text_color":"333333","profile_use_background_image":false,"default_profile":false,"default_profile_image":false,"following":false,"follow_request_sent":false,"notifications":false},{"id":22536055,"id_str":"22536055","name":"American Airlines","screen_name":"AmericanAir","location":"","profile_location":null,"description":"Thanks for checking in! We’re here to offer advice and inspiration for your trip on American. Please click here if you require a formal response to a complaint:","url":"http://t.co/hytC2LRHBG","entities":{"url":{"urls":[{"url":"http://t.co/hytC2LRHBG","expanded_url":"http://www.bit.ly/AACR1","display_url":"bit.ly/AACR1","indices":[0,22]}]},"description":{"urls":[]}},"protected":false,"followers_count":965875,"friends_count":49419,"listed_count":9536,"created_at":"Mon Mar 02 21:23:05 +0000 2009","favourites_count":3923,"utc_offset":-21600,"time_zone":"Central Time (US & Canada)","geo_enabled":false,"verified":true,"statuses_count":713933,"lang":"en","contributors_enabled":false,"is_translator":false,"is_translation_enabled":false,"profile_background_color":"FFFFFF","profile_background_image_url":"http://pbs.twimg.com/profile_background_images/766136889/7bf1ea573cf5b7b06e6ab83a67e4c8ef.jpeg","profile_background_image_url_https":"https://pbs.twimg.com/profile_background_images/766136889/7bf1ea573cf5b7b06e6ab83a67e4c8ef.jpeg","profile_background_tile":false,"profile_image_url":"http://pbs.twimg.com/profile_images/3120796848/abcdbcc86f46b4bc295e5aa1252ffcde_normal.jpeg","profile_image_url_https":"https://pbs.twimg.com/profile_images/3120796848/abcdbcc86f46b4bc295e5aa1252ffcde_normal.jpeg","profile_banner_url":"https://pbs.twimg.com/profile_banners/22536055/1413382875","profile_link_color":"276FC2","profile_sidebar_border_color":"FFFFFF","profile_sidebar_fill_color":"BEC9D4","profile_text_color":"333333","profile_use_background_image":true,"default_profile":false,"default_profile_image":false,"following":false,"follow_request_sent":false,"notifications":false},{"id":17219108,"id_str":"17219108","name":"Condé Nast Traveler","screen_name":"CNTraveler","location":"New York, NY","profile_location":null,"description":"At home in the world. #tasteintravel","url":"http://t.co/YFDkmtINYf","entities":{"url":{"urls":[{"url":"http://t.co/YFDkmtINYf","expanded_url":"http://www.cntraveler.com/","display_url":"cntraveler.com","indices":[0,22]}]},"description":{"urls":[]}},"protected":false,"followers_count":548253,"friends_count":45596,"listed_count":8623,"created_at":"Thu Nov 06 20:49:41 +0000 2008","favourites_count":1155,"utc_offset":-18000,"time_zone":"Eastern Time (US & Canada)","geo_enabled":false,"verified":true,"statuses_count":15362,"lang":"en","contributors_enabled":false,"is_translator":false,"is_translation_enabled":false,"profile_background_color":"FFFFFF","profile_background_image_url":"http://pbs.twimg.com/profile_background_images/431839704409849858/HhJXEESR.jpeg","profile_background_image_url_https":"https://pbs.twimg.com/profile_background_images/431839704409849858/HhJXEESR.jpeg","profile_background_tile":false,"profile_image_url":"http://pbs.twimg.com/profile_images/499269401607036928/6-zln9g1_normal.jpeg","profile_image_url_https":"https://pbs.twimg.com/profile_images/499269401607036928/6-zln9g1_normal.jpeg","profile_banner_url":"https://pbs.twimg.com/profile_banners/17219108/1414007763","profile_link_color":"0C67D4","profile_sidebar_border_color":"FFFFFF","profile_sidebar_fill_color":"DDEEF6","profile_text_color":"333333","profile_use_background_image":true,"default_profile":false,"default_profile_image":false,"following":false,"follow_request_sent":false,"notifications":false},{"id":14237001,"id_str":"14237001","name":"The Frugal Traveler","screen_name":"frugaltraveler","location":"Everywhere","profile_location":null,"description":"The New York Times' Frugal Traveler seeks out high style on a low budget. Our current columnist: Bonnie Tsui, @bonnietsui. (Profile image by Aurora King)","url":"http://t.co/pZI3CJoUqV","entities":{"url":{"urls":[{"url":"http://t.co/pZI3CJoUqV","expanded_url":"http://nytimes.com/frugaltraveler","display_url":"nytimes.com/frugaltraveler","indices":[0,22]}]},"description":{"urls":[]}},"protected":false,"followers_count":422957,"friends_count":264,"listed_count":6862,"created_at":"Thu Mar 27 17:22:27 +0000 2008","favourites_count":28,"utc_offset":-18000,"time_zone":"Eastern Time (US & Canada)","geo_enabled":true,"verified":false,"statuses_count":6757,"lang":"en","contributors_enabled":false,"is_translator":false,"is_translation_enabled":false,"profile_background_color":"FFFFFF","profile_background_image_url":"http://pbs.twimg.com/profile_background_images/5186798/P1030947.jpg","profile_background_image_url_https":"https://pbs.twimg.com/profile_background_images/5186798/P1030947.jpg","profile_background_tile":false,"profile_image_url":"http://pbs.twimg.com/profile_images/519187919089565697/H6ZsBDWR_normal.jpeg","profile_image_url_https":"https://pbs.twimg.com/profile_images/519187919089565697/H6ZsBDWR_normal.jpeg","profile_banner_url":"https://pbs.twimg.com/profile_banners/14237001/1412619183","profile_link_color":"0084B4","profile_sidebar_border_color":"BDDCAD","profile_sidebar_fill_color":"DDFFCC","profile_text_color":"333333","profile_use_background_image":true,"default_profile":false,"default_profile_image":false,"following":false,"follow_request_sent":false,"notifications":false},{"id":46207622,"id_str":"46207622","name":"Zagat Travel","screen_name":"ZagatTravel","location":"Around the world.","profile_location":null,"description":"The trusted and premier source for all things related to travel, hotels and spas.","url":"http://t.co/cAs5u1MJn1","entities":{"url":{"urls":[{"url":"http://t.co/cAs5u1MJn1","expanded_url":"http://blog.zagat.com/search/label/Travel","display_url":"blog.zagat.com/search/label/T…","indices":[0,22]}]},"description":{"urls":[]}},"protected":false,"followers_count":413751,"friends_count":15323,"listed_count":6437,"created_at":"Wed Jun 10 19:54:07 +0000 2009","favourites_count":35,"utc_offset":-18000,"time_zone":"Eastern Time (US & Canada)","geo_enabled":false,"verified":true,"statuses_count":10818,"lang":"en","contributors_enabled":false,"is_translator":false,"is_translation_enabled":false,"profile_background_color":"990C24","profile_background_image_url":"http://pbs.twimg.com/profile_background_images/838272927/b68376fa5da67bffa4276fe0f891ab68.jpeg","profile_background_image_url_https":"https://pbs.twimg.com/profile_background_images/838272927/b68376fa5da67bffa4276fe0f891ab68.jpeg","profile_background_tile":false,"profile_image_url":"http://pbs.twimg.com/profile_images/3498732105/43c93817bbdc1831631d0d10e274e5be_normal.png","profile_image_url_https":"https://pbs.twimg.com/profile_images/3498732105/43c93817bbdc1831631d0d10e274e5be_normal.png","profile_link_color":"96A0A3","profile_sidebar_border_color":"FFFFFF","profile_sidebar_fill_color":"DDFFCC","profile_text_color":"333333","profile_use_background_image":false,"default_profile":false,"default_profile_image":false,"following":false,"follow_request_sent":false,"notifications":false},{"id":6449282,"id_str":"6449282","name":"JetBlue Airways","screen_name":"JetBlue","location":"1-800-JETBLUE","profile_location":null,"description":"Hi, nice to tweet you! Fly with us to 85+ destinations and experience our award-winning service. For concerns that require a response, call or email.","url":"http://t.co/8TTR145Ow3","entities":{"url":{"urls":[{"url":"http://t.co/8TTR145Ow3","expanded_url":"http://www.jetblue.com","display_url":"jetblue.com","indices":[0,22]}]},"description":{"urls":[]}},"protected":false,"followers_count":1868561,"friends_count":107187,"listed_count":11586,"created_at":"Wed May 30 17:51:54 +0000 2007","favourites_count":2024,"utc_offset":-18000,"time_zone":"Eastern Time (US & Canada)","geo_enabled":true,"verified":true,"statuses_count":218907,"lang":"en","contributors_enabled":false,"is_translator":false,"is_translation_enabled":false,"profile_background_color":"8FCBED","profile_background_image_url":"http://pbs.twimg.com/profile_background_images/712543202/13f2df6c8ed5f703ccb0d94ab697853f.jpeg","profile_background_image_url_https":"https://pbs.twimg.com/profile_background_images/712543202/13f2df6c8ed5f703ccb0d94ab697853f.jpeg","profile_background_tile":false,"profile_image_url":"http://pbs.twimg.com/profile_images/378800000544221907/29fdb7f3b2141514d47c27c078a6d41d_normal.png","profile_image_url_https":"https://pbs.twimg.com/profile_images/378800000544221907/29fdb7f3b2141514d47c27c078a6d41d_normal.png","profile_banner_url":"https://pbs.twimg.com/profile_banners/6449282/1402928692","profile_link_color":"3399CC","profile_sidebar_border_color":"FFFFFF","profile_sidebar_fill_color":"EEEEEE","profile_text_color":"999999","profile_use_background_image":true,"default_profile":false,"default_profile_image":false,"following":false,"follow_request_sent":false,"notifications":false},{"id":15649433,"id_str":"15649433","name":"Travel - State Dept","screen_name":"TravelGov","location":"Washington, DC, USA","profile_location":null,"description":"Official Twitter for U.S. Department of State Bureau of Consular Affairs: protecting lives and interests of U.S. citizens overseas. Currently on Duty: Nicole","url":"http://t.co/xJDfcCCRJw","entities":{"url":{"urls":[{"url":"http://t.co/xJDfcCCRJw","expanded_url":"http://travel.state.gov","display_url":"travel.state.gov","indices":[0,22]}]},"description":{"urls":[]}},"protected":false,"followers_count":418186,"friends_count":468,"listed_count":6911,"created_at":"Tue Jul 29 18:38:44 +0000 2008","favourites_count":251,"utc_offset":-18000,"time_zone":"Eastern Time (US & Canada)","geo_enabled":true,"verified":true,"statuses_count":3760,"lang":"en","contributors_enabled":false,"is_translator":false,"is_translation_enabled":false,"profile_background_color":"083680","profile_background_image_url":"http://pbs.twimg.com/profile_background_images/85788649/passportdayusa.jpg","profile_background_image_url_https":"https://pbs.twimg.com/profile_background_images/85788649/passportdayusa.jpg","profile_background_tile":false,"profile_image_url":"http://pbs.twimg.com/profile_images/933275449/TravelGov_logo_normal.gif","profile_image_url_https":"https://pbs.twimg.com/profile_images/933275449/TravelGov_logo_normal.gif","profile_banner_url":"https://pbs.twimg.com/profile_banners/15649433/1412702582","profile_link_color":"4A8EBF","profile_sidebar_border_color":"FFFFFF","profile_sidebar_fill_color":"BDB9BD","profile_text_color":"031414","profile_use_background_image":false,"default_profile":false,"default_profile_image":false,"following":false,"follow_request_sent":false,"notifications":false},{"id":9676212,"id_str":"9676212","name":"L.A. Times Travel","screen_name":"latimestravel","location":"Los Angeles, CA","profile_location":null,"description":"@LATimes Travel news, tips, reviews and deals from Christopher Reynolds (@mrcsreynolds), Catharine Hamm (@CatHamm) and Brady MacDonald @latimesfunland)","url":"http://t.co/hEjEOdxHHq","entities":{"url":{"urls":[{"url":"http://t.co/hEjEOdxHHq","expanded_url":"http://www.latimes.com/travel","display_url":"latimes.com/travel","indices":[0,22]}]},"description":{"urls":[]}},"protected":false,"followers_count":328124,"friends_count":4229,"listed_count":4959,"created_at":"Thu Oct 25 05:30:05 +0000 2007","favourites_count":66,"utc_offset":-28800,"time_zone":"Pacific Time (US & Canada)","geo_enabled":false,"verified":true,"statuses_count":11816,"lang":"en","contributors_enabled":false,"is_translator":false,"is_translation_enabled":false,"profile_background_color":"FFFFFF","profile_background_image_url":"http://pbs.twimg.com/profile_background_images/35863513/09AUD140_Twitter_Background.jpg","profile_background_image_url_https":"https://pbs.twimg.com/profile_background_images/35863513/09AUD140_Twitter_Background.jpg","profile_background_tile":false,"profile_image_url":"http://pbs.twimg.com/profile_images/1895031710/Travel_normal.jpg","profile_image_url_https":"https://pbs.twimg.com/profile_images/1895031710/Travel_normal.jpg","profile_banner_url":"https://pbs.twimg.com/profile_banners/9676212/1400694234","profile_link_color":"0000FF","profile_sidebar_border_color":"FFFFFF","profile_sidebar_fill_color":"FFFFFF","profile_text_color":"000000","profile_use_background_image":false,"default_profile":false,"default_profile_image":false,"following":false,"follow_request_sent":false,"notifications":false},{"id":10937622,"id_str":"10937622","name":"airfarewatchdog","screen_name":"airfarewatchdog","location":"We travel a lot!","profile_location":null,"description":"The only low airfare alert site that covers all airlines. Twitterer-in-chief: @georgehobica. A TripAdvisor Media Group website.","url":"http://t.co/VgbqO7Aq8L","entities":{"url":{"urls":[{"url":"http://t.co/VgbqO7Aq8L","expanded_url":"http://www.airfarewatchdog.com","display_url":"airfarewatchdog.com","indices":[0,22]}]},"description":{"urls":[]}},"protected":false,"followers_count":441035,"friends_count":43240,"listed_count":6015,"created_at":"Fri Dec 07 15:12:56 +0000 2007","favourites_count":737,"utc_offset":-21600,"time_zone":"Central Time (US & Canada)","geo_enabled":true,"verified":true,"statuses_count":33671,"lang":"en","contributors_enabled":false,"is_translator":false,"is_translation_enabled":false,"profile_background_color":"E5F4FF","profile_background_image_url":"http://pbs.twimg.com/profile_background_images/62451073/AFWD-bg.jpg","profile_background_image_url_https":"https://pbs.twimg.com/profile_background_images/62451073/AFWD-bg.jpg","profile_background_tile":false,"profile_image_url":"http://pbs.twimg.com/profile_images/220756397/AFWD-twitter-logo_normal.gif","profile_image_url_https":"https://pbs.twimg.com/profile_images/220756397/AFWD-twitter-logo_normal.gif","profile_banner_url":"https://pbs.twimg.com/profile_banners/10937622/1406640604","profile_link_color":"0084B4","profile_sidebar_border_color":"BDDCAD","profile_sidebar_fill_color":"DDFFCC","profile_text_color":"333333","profile_use_background_image":true,"default_profile":false,"default_profile_image":false,"following":false,"follow_request_sent":false,"notifications":false},{"id":16031536,"id_str":"16031536","name":"Fodor's Travel","screen_name":"fodorstravel","location":"New York / Traveling the world","profile_location":null,"description":"Travel Intelligence to give you insightful observations and recommendations to plan your next getaway.","url":"http://t.co/9B2oYDUOdI","entities":{"url":{"urls":[{"url":"http://t.co/9B2oYDUOdI","expanded_url":"http://www.fodors.com","display_url":"fodors.com","indices":[0,22]}]},"description":{"urls":[]}},"protected":false,"followers_count":413336,"friends_count":3360,"listed_count":6326,"created_at":"Thu Aug 28 19:34:11 +0000 2008","favourites_count":609,"utc_offset":-18000,"time_zone":"Eastern Time (US & Canada)","geo_enabled":true,"verified":true,"statuses_count":7724,"lang":"en","contributors_enabled":false,"is_translator":false,"is_translation_enabled":false,"profile_background_color":"B6D6F0","profile_background_image_url":"http://pbs.twimg.com/profile_background_images/757989745/94ddf468ef006e580947c5a700044fa6.jpeg","profile_background_image_url_https":"https://pbs.twimg.com/profile_background_images/757989745/94ddf468ef006e580947c5a700044fa6.jpeg","profile_background_tile":false,"profile_image_url":"http://pbs.twimg.com/profile_images/3079362282/5622e1cc818b5dfb738ffec6b4936d71_normal.png","profile_image_url_https":"https://pbs.twimg.com/profile_images/3079362282/5622e1cc818b5dfb738ffec6b4936d71_normal.png","profile_banner_url":"https://pbs.twimg.com/profile_banners/16031536/1411051498","profile_link_color":"0088FF","profile_sidebar_border_color":"FFFFFF","profile_sidebar_fill_color":"FBFBFB","profile_text_color":"333333","profile_use_background_image":true,"default_profile":false,"default_profile_image":false,"following":false,"follow_request_sent":false,"notifications":false},{"id":21887420,"id_str":"21887420","name":"Guardian Travel","screen_name":"GuardianTravel","location":"","profile_location":null,"description":"The latest travel news, insider guides, emerging destinations, new hotels and travel trends from the Guardian\r\n\r\nFollow us on http://t.co/hMxwLpVRAb","url":"http://t.co/JvRPQUrjDg","entities":{"url":{"urls":[{"url":"http://t.co/JvRPQUrjDg","expanded_url":"http://www.theguardian.com/travel","display_url":"theguardian.com/travel","indices":[0,22]}]},"description":{"urls":[{"url":"http://t.co/hMxwLpVRAb","expanded_url":"http://instagram.com/guardiantravelsnaps","display_url":"instagram.com/guardiantravel…","indices":[126,148]}]}},"protected":false,"followers_count":458981,"friends_count":345,"listed_count":6354,"created_at":"Wed Feb 25 16:59:14 +0000 2009","favourites_count":159,"utc_offset":0,"time_zone":"London","geo_enabled":true,"verified":false,"statuses_count":12077,"lang":"en","contributors_enabled":false,"is_translator":false,"is_translation_enabled":false,"profile_background_color":"89C9FA","profile_background_image_url":"http://pbs.twimg.com/profile_background_images/510429647318695936/L2n4iZqU.jpeg","profile_background_image_url_https":"https://pbs.twimg.com/profile_background_images/510429647318695936/L2n4iZqU.jpeg","profile_background_tile":true,"profile_image_url":"http://pbs.twimg.com/profile_images/512932274044551168/Zthwyl38_normal.jpeg","profile_image_url_https":"https://pbs.twimg.com/profile_images/512932274044551168/Zthwyl38_normal.jpeg","profile_banner_url":"https://pbs.twimg.com/profile_banners/21887420/1410530648","profile_link_color":"89C9FA","profile_sidebar_border_color":"FFFFFF","profile_sidebar_fill_color":"CAE3F3","profile_text_color":"333333","profile_use_background_image":false,"default_profile":false,"default_profile_image":false,"following":false,"follow_request_sent":false,"notifications":false},{"id":10933662,"id_str":"10933662","name":"The Times Travel","screen_name":"timestravel","location":"London","profile_location":null,"description":"The latest travel news, deals and videos plus inspiration for your next trip","url":"http://t.co/EPsjNir63E","entities":{"url":{"urls":[{"url":"http://t.co/EPsjNir63E","expanded_url":"http://www.thetimes.co.uk/tto/travel/","display_url":"thetimes.co.uk/tto/travel/","indices":[0,22]}]},"description":{"urls":[]}},"protected":false,"followers_count":375803,"friends_count":33431,"listed_count":4966,"created_at":"Fri Dec 07 12:31:46 +0000 2007","favourites_count":47,"utc_offset":0,"time_zone":"London","geo_enabled":false,"verified":false,"statuses_count":4324,"lang":"en","contributors_enabled":false,"is_translator":false,"is_translation_enabled":false,"profile_background_color":"EFEFEF","profile_background_image_url":"http://pbs.twimg.com/profile_background_images/791534715/045c3fadaacbb35147cac3fa14bbda6d.png","profile_background_image_url_https":"https://pbs.twimg.com/profile_background_images/791534715/045c3fadaacbb35147cac3fa14bbda6d.png","profile_background_tile":true,"profile_image_url":"http://pbs.twimg.com/profile_images/3257011063/5301e773df76877d775a3a1fde1be669_normal.png","profile_image_url_https":"https://pbs.twimg.com/profile_images/3257011063/5301e773df76877d775a3a1fde1be669_normal.png","profile_banner_url":"https://pbs.twimg.com/profile_banners/10933662/1360944013","profile_link_color":"732D6E","profile_sidebar_border_color":"FFFFFF","profile_sidebar_fill_color":"FFFFFF","profile_text_color":"000000","profile_use_background_image":true,"default_profile":false,"default_profile_image":false,"following":false,"follow_request_sent":false,"notifications":false},{"id":17416571,"id_str":"17416571","name":"Airbnb","screen_name":"Airbnb","location":"","profile_location":null,"description":"Airbnb is the world's largest community-driven hospitality company. With unique listings in 190 countries, travelers can belong anywhere.","url":"http://t.co/lAeftY6Y79","entities":{"url":{"urls":[{"url":"http://t.co/lAeftY6Y79","expanded_url":"http://www.airbnb.com","display_url":"airbnb.com","indices":[0,22]}]},"description":{"urls":[]}},"protected":false,"followers_count":280106,"friends_count":20542,"listed_count":3872,"created_at":"Sun Nov 16 02:10:58 +0000 2008","favourites_count":6473,"utc_offset":-28800,"time_zone":"Pacific Time (US & Canada)","geo_enabled":false,"verified":true,"statuses_count":22711,"lang":"en","contributors_enabled":false,"is_translator":false,"is_translation_enabled":false,"profile_background_color":"FFFFFF","profile_background_image_url":"http://pbs.twimg.com/profile_background_images/489469482444660736/ZOAIHxJp.jpeg","profile_background_image_url_https":"https://pbs.twimg.com/profile_background_images/489469482444660736/ZOAIHxJp.jpeg","profile_background_tile":false,"profile_image_url":"http://pbs.twimg.com/profile_images/489464150406340609/426IVfsr_normal.jpeg","profile_image_url_https":"https://pbs.twimg.com/profile_images/489464150406340609/426IVfsr_normal.jpeg","profile_banner_url":"https://pbs.twimg.com/profile_banners/17416571/1405532331","profile_link_color":"1D95CB","profile_sidebar_border_color":"FFFFFF","profile_sidebar_fill_color":"F7F7F7","profile_text_color":"787878","profile_use_background_image":true,"default_profile":false,"default_profile_image":false,"following":false,"follow_request_sent":false,"notifications":false},{"id":19789299,"id_str":"19789299","name":"Peter S. Greenberg","screen_name":"PeterSGreenberg","location":"","profile_location":null,"description":"Travel Editor for CBS News ♦ Subscribe to the Travel Today podcast http://t.co/Y6VGl6OkP7","url":"http://t.co/iwaAsouoLd","entities":{"url":{"urls":[{"url":"http://t.co/iwaAsouoLd","expanded_url":"http://www.PeterGreenberg.com","display_url":"PeterGreenberg.com","indices":[0,22]}]},"description":{"urls":[{"url":"http://t.co/Y6VGl6OkP7","expanded_url":"http://bit.ly/1mKSV3h","display_url":"bit.ly/1mKSV3h","indices":[67,89]}]}},"protected":false,"followers_count":223482,"friends_count":736,"listed_count":3965,"created_at":"Fri Jan 30 21:20:28 +0000 2009","favourites_count":28,"utc_offset":-32400,"time_zone":"Alaska","geo_enabled":false,"verified":true,"statuses_count":21878,"lang":"en","contributors_enabled":false,"is_translator":false,"is_translation_enabled":false,"profile_background_color":"F4F6F7","profile_background_image_url":"http://pbs.twimg.com/profile_background_images/734692561/7e45c8aa7deb79ec15d61710a4893c96.jpeg","profile_background_image_url_https":"https://pbs.twimg.com/profile_background_images/734692561/7e45c8aa7deb79ec15d61710a4893c96.jpeg","profile_background_tile":true,"profile_image_url":"http://pbs.twimg.com/profile_images/451418692799066112/qhYiwDPl_normal.jpeg","profile_image_url_https":"https://pbs.twimg.com/profile_images/451418692799066112/qhYiwDPl_normal.jpeg","profile_banner_url":"https://pbs.twimg.com/profile_banners/19789299/1398459327","profile_link_color":"D02B55","profile_sidebar_border_color":"FFFFFF","profile_sidebar_fill_color":"99CC33","profile_text_color":"3E4415","profile_use_background_image":true,"default_profile":false,"default_profile_image":false,"following":false,"follow_request_sent":false,"notifications":false},{"id":22847499,"id_str":"22847499","name":"Not For Tourists","screen_name":"notfortourists","location":"Your Neighborhood","profile_location":null,"description":"The ultimate urban neighborhood guide for you, not them.","url":"http://t.co/C8WBJyxh3C","entities":{"url":{"urls":[{"url":"http://t.co/C8WBJyxh3C","expanded_url":"http://notfortourists.com/","display_url":"notfortourists.com","indices":[0,22]}]},"description":{"urls":[]}},"protected":false,"followers_count":256347,"friends_count":2678,"listed_count":3428,"created_at":"Wed Mar 04 22:40:54 +0000 2009","favourites_count":24,"utc_offset":-18000,"time_zone":"Eastern Time (US & Canada)","geo_enabled":true,"verified":true,"statuses_count":6721,"lang":"en","contributors_enabled":false,"is_translator":false,"is_translation_enabled":false,"profile_background_color":"D7CFCC","profile_background_image_url":"http://pbs.twimg.com/profile_background_images/23878099/twitter2.jpg","profile_background_image_url_https":"https://pbs.twimg.com/profile_background_images/23878099/twitter2.jpg","profile_background_tile":false,"profile_image_url":"http://pbs.twimg.com/profile_images/519194865981063169/mCzAQpPn_normal.jpeg","profile_image_url_https":"https://pbs.twimg.com/profile_images/519194865981063169/mCzAQpPn_normal.jpeg","profile_banner_url":"https://pbs.twimg.com/profile_banners/22847499/1401479204","profile_link_color":"F85F1B","profile_sidebar_border_color":"FFFFFF","profile_sidebar_fill_color":"F5F5F5","profile_text_color":"000000","profile_use_background_image":true,"default_profile":false,"default_profile_image":false,"following":false,"follow_request_sent":false,"notifications":false},{"id":19381755,"id_str":"19381755","name":"Brett Snyder","screen_name":"crankyflier","location":"Long Beach, CA","profile_location":null,"description":"I write The Cranky Flier, a snarky consumer air travel blog.  Yes, I'm an airline dork.","url":"http://t.co/yDgCgGXq1z","entities":{"url":{"urls":[{"url":"http://t.co/yDgCgGXq1z","expanded_url":"http://crankyflier.com/","display_url":"crankyflier.com","indices":[0,22]}]},"description":{"urls":[]}},"protected":false,"followers_count":149642,"friends_count":251,"listed_count":2039,"created_at":"Fri Jan 23 04:44:01 +0000 2009","favourites_count":97,"utc_offset":-28800,"time_zone":"Pacific Time (US & Canada)","geo_enabled":false,"verified":false,"statuses_count":12111,"lang":"en","contributors_enabled":false,"is_translator":false,"is_translation_enabled":false,"profile_background_color":"669944","profile_background_image_url":"http://pbs.twimg.com/profile_background_images/4126070/crankyflier_logoFinalsmall.PNG","profile_background_image_url_https":"https://pbs.twimg.com/profile_background_images/4126070/crankyflier_logoFinalsmall.PNG","profile_background_tile":false,"profile_image_url":"http://pbs.twimg.com/profile_images/494544322029555713/4ojbBw9B_normal.jpeg","profile_image_url_https":"https://pbs.twimg.com/profile_images/494544322029555713/4ojbBw9B_normal.jpeg","profile_link_color":"0000FF","profile_sidebar_border_color":"669944","profile_sidebar_fill_color":"EAEAEA","profile_text_color":"000000","profile_use_background_image":true,"default_profile":false,"default_profile_image":false,"following":false,"follow_request_sent":false,"notifications":false},{"id":14140913,"id_str":"14140913","name":"Marriott Internat'l","screen_name":"MarriottIntl","location":"Bethesda, Maryland","profile_location":null,"description":"Marriott International is a global lodging leader with more than 4,000 hotels in 78 countries.","url":"http://t.co/9W0bGpPYuG","entities":{"url":{"urls":[{"url":"http://t.co/9W0bGpPYuG","expanded_url":"http://www.marriott.com","display_url":"marriott.com","indices":[0,22]}]},"description":{"urls":[]}},"protected":false,"followers_count":342335,"friends_count":15903,"listed_count":4222,"created_at":"Thu Mar 13 17:21:27 +0000 2008","favourites_count":10974,"utc_offset":-18000,"time_zone":"Eastern Time (US & Canada)","geo_enabled":true,"verified":true,"statuses_count":18966,"lang":"en","contributors_enabled":false,"is_translator":false,"is_translation_enabled":false,"profile_background_color":"C0DEED","profile_background_image_url":"http://pbs.twimg.com/profile_background_images/378800000060250903/8a79c26233cbc5a085b98752690fd5cf.jpeg","profile_background_image_url_https":"https://pbs.twimg.com/profile_background_images/378800000060250903/8a79c26233cbc5a085b98752690fd5cf.jpeg","profile_background_tile":false,"profile_image_url":"http://pbs.twimg.com/profile_images/2936408233/1fc0afb0e7297b95c2633fdad525381a_normal.jpeg","profile_image_url_https":"https://pbs.twimg.com/profile_images/2936408233/1fc0afb0e7297b95c2633fdad525381a_normal.jpeg","profile_banner_url":"https://pbs.twimg.com/profile_banners/14140913/1398187908","profile_link_color":"0000FF","profile_sidebar_border_color":"FFFFFF","profile_sidebar_fill_color":"FFFFFF","profile_text_color":"000000","profile_use_background_image":true,"default_profile":false,"default_profile_image":false,"following":false,"follow_request_sent":false,"notifications":false},{"id":14076231,"id_str":"14076231","name":"Gadling","screen_name":"Gadling","location":"The World","profile_location":null,"description":"We write about fun, interesting & relevant travel.","url":"http://t.co/yxl0eRk6DI","entities":{"url":{"urls":[{"url":"http://t.co/yxl0eRk6DI","expanded_url":"http://gadling.com","display_url":"gadling.com","indices":[0,22]}]},"description":{"urls":[]}},"protected":false,"followers_count":192177,"friends_count":1808,"listed_count":4042,"created_at":"Tue Mar 04 04:03:41 +0000 2008","favourites_count":14,"utc_offset":-18000,"time_zone":"Eastern Time (US & Canada)","geo_enabled":false,"verified":true,"statuses_count":25233,"lang":"en","contributors_enabled":false,"is_translator":false,"is_translation_enabled":false,"profile_background_color":"E3E1D2","profile_background_image_url":"http://pbs.twimg.com/profile_background_images/3140298/bg-body-globe.jpg","profile_background_image_url_https":"https://pbs.twimg.com/profile_background_images/3140298/bg-body-globe.jpg","profile_background_tile":false,"profile_image_url":"http://pbs.twimg.com/profile_images/509772087368900608/hl_HQXZB_normal.jpeg","profile_image_url_https":"https://pbs.twimg.com/profile_images/509772087368900608/hl_HQXZB_normal.jpeg","profile_banner_url":"https://pbs.twimg.com/profile_banners/14076231/1411926770","profile_link_color":"0084B4","profile_sidebar_border_color":"FFFFFF","profile_sidebar_fill_color":"DDF9E4","profile_text_color":"333333","profile_use_background_image":true,"default_profile":false,"default_profile_image":false,"following":false,"follow_request_sent":false,"notifications":false},{"id":15811202,"id_str":"15811202","name":"Ben Mutzabaugh","screen_name":"TodayInTheSky","location":"Washington, DC","profile_location":null,"description":"Get the latest airline industry news from USA TODAY's Ben Mutzabaugh in his Today In The Sky blog brought to you by http://t.co/sIDYyrTwdr.","url":"http://t.co/729gSJx04M","entities":{"url":{"urls":[{"url":"http://t.co/729gSJx04M","expanded_url":"http://www.usatoday.com/travel/flights/blog.aspx","display_url":"usatoday.com/travel/flights…","indices":[0,22]}]},"description":{"urls":[{"url":"http://t.co/sIDYyrTwdr","expanded_url":"http://USATODAY.com","display_url":"USATODAY.com","indices":[116,138]}]}},"protected":false,"followers_count":175185,"friends_count":693,"listed_count":2279,"created_at":"Mon Aug 11 18:08:45 +0000 2008","favourites_count":292,"utc_offset":-18000,"time_zone":"Eastern Time (US & Canada)","geo_enabled":true,"verified":true,"statuses_count":10217,"lang":"en","contributors_enabled":false,"is_translator":false,"is_translation_enabled":false,"profile_background_color":"2BC3E9","profile_background_image_url":"http://pbs.twimg.com/profile_background_images/378800000092308991/d8aa5949bf34d8f8431799c7b10bee67.jpeg","profile_background_image_url_https":"https://pbs.twimg.com/profile_background_images/378800000092308991/d8aa5949bf34d8f8431799c7b10bee67.jpeg","profile_background_tile":false,"profile_image_url":"http://pbs.twimg.com/profile_images/464075937030496256/vCbk4FSZ_normal.png","profile_image_url_https":"https://pbs.twimg.com/profile_images/464075937030496256/vCbk4FSZ_normal.png","profile_banner_url":"https://pbs.twimg.com/profile_banners/15811202/1415030730","profile_link_color":"0000FF","profile_sidebar_border_color":"FFFFFF","profile_sidebar_fill_color":"B8E9F0","profile_text_color":"000000","profile_use_background_image":true,"default_profile":false,"default_profile_image":false,"following":false,"follow_request_sent":false,"notifications":false},{"id":16126957,"id_str":"16126957","name":"paul steele","screen_name":"paul_steele","location":"UK","profile_location":null,"description":"BaldHiker and Bald Traveller. Wanderer. Founder/Editor http://t.co/xNKXPy9o5V Contact via site. Travel, Photography, Nature. - About me: http://t.co/Lt0i7Ap0ZV","url":"http://t.co/DcxPuiYbfG","entities":{"url":{"urls":[{"url":"http://t.co/DcxPuiYbfG","expanded_url":"http://www.baldhiker.com/","display_url":"baldhiker.com","indices":[0,22]}]},"description":{"urls":[{"url":"http://t.co/xNKXPy9o5V","expanded_url":"http://BaldHiker.com","display_url":"BaldHiker.com","indices":[55,77]},{"url":"http://t.co/Lt0i7Ap0ZV","expanded_url":"http://www.baldhiker.com/about-us/","display_url":"baldhiker.com/about-us/","indices":[137,159]}]}},"protected":false,"followers_count":612230,"friends_count":232638,"listed_count":10482,"created_at":"Thu Sep 04 09:10:29 +0000 2008","favourites_count":3149,"utc_offset":0,"time_zone":"London","geo_enabled":false,"verified":false,"statuses_count":204899,"lang":"en","contributors_enabled":false,"is_translator":false,"is_translation_enabled":false,"profile_background_color":"56B5ED","profile_background_image_url":"http://pbs.twimg.com/profile_background_images/672648755/8aa2e5d7e1ee22adb319817ea5d5fc80.jpeg","profile_background_image_url_https":"https://pbs.twimg.com/profile_background_images/672648755/8aa2e5d7e1ee22adb319817ea5d5fc80.jpeg","profile_background_tile":false,"profile_image_url":"http://pbs.twimg.com/profile_images/378800000408452063/d12becd7df3503c53b3227534e994b55_normal.jpeg","profile_image_url_https":"https://pbs.twimg.com/profile_images/378800000408452063/d12becd7df3503c53b3227534e994b55_normal.jpeg","profile_banner_url":"https://pbs.twimg.com/profile_banners/16126957/1398236652","profile_link_color":"56B5ED","profile_sidebar_border_color":"FFFFFF","profile_sidebar_fill_color":"DDFFCC","profile_text_color":"333333","profile_use_background_image":true,"default_profile":false,"default_profile_image":false,"following":false,"follow_request_sent":false,"notifications":false},{"id":1930311,"id_str":"1930311","name":"Vagabondish.com","screen_name":"vagabondish","location":"Massachusetts","profile_location":null,"description":"Offbeat world news and dubious travel advice, tips and how-to's from travel geek @AliceNaser (^an) + founding editor/resident smartass @MikeRichard","url":"http://t.co/VwDTsaVPt5","entities":{"url":{"urls":[{"url":"http://t.co/VwDTsaVPt5","expanded_url":"http://www.vagabondish.com","display_url":"vagabondish.com","indices":[0,22]}]},"description":{"urls":[]}},"protected":false,"followers_count":190425,"friends_count":4669,"listed_count":3390,"created_at":"Thu Mar 22 19:52:02 +0000 2007","favourites_count":244,"utc_offset":-18000,"time_zone":"Eastern Time (US & Canada)","geo_enabled":true,"verified":false,"statuses_count":17198,"lang":"en","contributors_enabled":false,"is_translator":false,"is_translation_enabled":false,"profile_background_color":"FDF8E8","profile_background_image_url":"http://pbs.twimg.com/profile_background_images/874688023/1ac359da354d8e414b0e1f2c4b5404e4.jpeg","profile_background_image_url_https":"https://pbs.twimg.com/profile_background_images/874688023/1ac359da354d8e414b0e1f2c4b5404e4.jpeg","profile_background_tile":false,"profile_image_url":"http://pbs.twimg.com/profile_images/1786122783/hipgeo_-_profile_normal.jpg","profile_image_url_https":"https://pbs.twimg.com/profile_images/1786122783/hipgeo_-_profile_normal.jpg","profile_banner_url":"https://pbs.twimg.com/profile_banners/1930311/1398345613","profile_link_color":"117296","profile_sidebar_border_color":"FFFFFF","profile_sidebar_fill_color":"F3E9D6","profile_text_color":"333333","profile_use_background_image":true,"default_profile":false,"default_profile_image":false,"following":false,"follow_request_sent":false,"notifications":false},{"id":15182728,"id_str":"15182728","name":"STA Travel U.S.","screen_name":"statravelUS","location":"Dallas, TX","profile_location":null,"description":"The official home of STA Travel US. Tweeting deals, flash sales and great advice. Tweets by @teresacordov","url":"http://t.co/BHwHAsL6Lb","entities":{"url":{"urls":[{"url":"http://t.co/BHwHAsL6Lb","expanded_url":"http://sta.travel/1oH1pEc","display_url":"sta.travel/1oH1pEc","indices":[0,22]}]},"description":{"urls":[]}},"protected":false,"followers_count":184681,"friends_count":2116,"listed_count":1971,"created_at":"Fri Jun 20 18:26:45 +0000 2008","favourites_count":579,"utc_offset":-21600,"time_zone":"Central Time (US & Canada)","geo_enabled":true,"verified":true,"statuses_count":6667,"lang":"en","contributors_enabled":false,"is_translator":false,"is_translation_enabled":false,"profile_background_color":"FFFFFF","profile_background_image_url":"http://pbs.twimg.com/profile_background_images/483714198661107712/pEssgyf_.jpeg","profile_background_image_url_https":"https://pbs.twimg.com/profile_background_images/483714198661107712/pEssgyf_.jpeg","profile_background_tile":false,"profile_image_url":"http://pbs.twimg.com/profile_images/479278763125915648/_x30yGV8_normal.png","profile_image_url_https":"https://pbs.twimg.com/profile_images/479278763125915648/_x30yGV8_normal.png","profile_banner_url":"https://pbs.twimg.com/profile_banners/15182728/1412217841","profile_link_color":"0065BD","profile_sidebar_border_color":"FFFFFF","profile_sidebar_fill_color":"EFEFEF","profile_text_color":"0065BD","profile_use_background_image":true,"default_profile":false,"default_profile_image":false,"following":false,"follow_request_sent":false,"notifications":false},{"id":15811314,"id_str":"15811314","name":"WBTW: LuxuryTravel","screen_name":"WeBlogtheWorld","location":"San Francisco","profile_location":null,"description":"Online Luxury Travel & Adventure Travel Magazine covering unique experiences in travel, culture, adventure, food/wine, arts & more. Join the community!","url":"http://t.co/dzVORXmIFM","entities":{"url":{"urls":[{"url":"http://t.co/dzVORXmIFM","expanded_url":"http://www.weblogtheworld.com","display_url":"weblogtheworld.com","indices":[0,22]}]},"description":{"urls":[]}},"protected":false,"followers_count":867102,"friends_count":102559,"listed_count":5776,"created_at":"Mon Aug 11 18:16:54 +0000 2008","favourites_count":738,"utc_offset":-28800,"time_zone":"Pacific Time (US & Canada)","geo_enabled":false,"verified":false,"statuses_count":27250,"lang":"en","contributors_enabled":false,"is_translator":false,"is_translation_enabled":false,"profile_background_color":"164E64","profile_background_image_url":"http://pbs.twimg.com/profile_background_images/660541232/xotzo0v5bzb34s44zqzk.jpeg","profile_background_image_url_https":"https://pbs.twimg.com/profile_background_images/660541232/xotzo0v5bzb34s44zqzk.jpeg","profile_background_tile":false,"profile_image_url":"http://pbs.twimg.com/profile_images/2615469788/hc8ufw9zhxnsz9mr5u06_normal.jpeg","profile_image_url_https":"https://pbs.twimg.com/profile_images/2615469788/hc8ufw9zhxnsz9mr5u06_normal.jpeg","profile_banner_url":"https://pbs.twimg.com/profile_banners/15811314/1401784235","profile_link_color":"0084B4","profile_sidebar_border_color":"32362F","profile_sidebar_fill_color":"A07F2D","profile_text_color":"121010","profile_use_background_image":true,"default_profile":false,"default_profile_image":false,"following":false,"follow_request_sent":false,"notifications":false},{"id":31240434,"id_str":"31240434","name":"Wynn Las Vegas","screen_name":"WynnLasVegas","location":"Las Vegas","profile_location":null,"description":"A luxury Las Vegas resort. Offering award-winning rooms & suites, signature restaurants, exciting leisure activities & nightly entertainment.","url":"http://t.co/kHhkjaug10","entities":{"url":{"urls":[{"url":"http://t.co/kHhkjaug10","expanded_url":"http://wyn.lv/WynnLasVegas","display_url":"wyn.lv/WynnLasVegas","indices":[0,22]}]},"description":{"urls":[]}},"protected":false,"followers_count":558767,"friends_count":8680,"listed_count":4027,"created_at":"Tue Apr 14 21:59:32 +0000 2009","favourites_count":2914,"utc_offset":-28800,"time_zone":"Pacific Time (US & Canada)","geo_enabled":false,"verified":true,"statuses_count":11558,"lang":"en","contributors_enabled":false,"is_translator":false,"is_translation_enabled":false,"profile_background_color":"000000","profile_background_image_url":"http://pbs.twimg.com/profile_background_images/448906916/1010_WynnTwitterSkinFinal.jpg","profile_background_image_url_https":"https://pbs.twimg.com/profile_background_images/448906916/1010_WynnTwitterSkinFinal.jpg","profile_background_tile":false,"profile_image_url":"http://pbs.twimg.com/profile_images/1896772205/WynnTwitterAvatarFinal_normal.jpg","profile_image_url_https":"https://pbs.twimg.com/profile_images/1896772205/WynnTwitterAvatarFinal_normal.jpg","profile_banner_url":"https://pbs.twimg.com/profile_banners/31240434/1407963965","profile_link_color":"585757","profile_sidebar_border_color":"FFFFFF","profile_sidebar_fill_color":"F0ECDF","profile_text_color":"66563D","profile_use_background_image":true,"default_profile":false,"default_profile_image":false,"following":false,"follow_request_sent":false,"notifications":false},{"id":36065771,"id_str":"36065771","name":"Condé Nast Traveller","screen_name":"cntraveller","location":"London, UK","profile_location":null,"description":"Travel inspiration from the editors of Condé Nast Traveller UK","url":"http://t.co/vxkFs5qvR5","entities":{"url":{"urls":[{"url":"http://t.co/vxkFs5qvR5","expanded_url":"http://www.cntraveller.com","display_url":"cntraveller.com","indices":[0,22]}]},"description":{"urls":[]}},"protected":false,"followers_count":338953,"friends_count":34,"listed_count":4350,"created_at":"Tue Apr 28 13:37:05 +0000 2009","favourites_count":61,"utc_offset":0,"time_zone":"London","geo_enabled":false,"verified":true,"statuses_count":30247,"lang":"en","contributors_enabled":false,"is_translator":false,"is_translation_enabled":false,"profile_background_color":"56DBED","profile_background_image_url":"http://pbs.twimg.com/profile_background_images/70215292/Twitter_bkgd_3.jpg","profile_background_image_url_https":"https://pbs.twimg.com/profile_background_images/70215292/Twitter_bkgd_3.jpg","profile_background_tile":false,"profile_image_url":"http://pbs.twimg.com/profile_images/486171939291922432/wgMk_ESI_normal.jpeg","profile_image_url_https":"https://pbs.twimg.com/profile_images/486171939291922432/wgMk_ESI_normal.jpeg","profile_banner_url":"https://pbs.twimg.com/profile_banners/36065771/1399479319","profile_link_color":"D02B54","profile_sidebar_border_color":"FFFFFF","profile_sidebar_fill_color":"CEEAE2","profile_text_color":"333333","profile_use_background_image":false,"default_profile":false,"default_profile_image":false,"following":false,"follow_request_sent":false,"notifications":false}],"size":44,"slug":"travel","name":"Travel"}